Workbook

Sheet Orders
A1: order_id | B1: order_date | C1: customer_id | D1: product_id | E1: sales_rep_id | F1: quantity | G1: unit_price | H1: discount_pct | I1: final_amount | J1: payment_status | K1: ship_city
A2: ORD-00001 | B2: 45549 | C2: CUST-0243 | D2: PROD-014 | E2: R007 | F2: 8 | G2: 3620 | H2: 15.4 | I2: 24500.16 | J2: Completed | K2: Pune
A3: ORD-00002 | B3: 45340 | C3: CUST-0202 | D3: PROD-020 | E3: R005 | F3: 2 | G3: 820 | H3: 10.8 | I3: 1462.88 | J3: Pending | K3: Chennai
A4: ORD-00003 | B4: 45371 | C4: CUST-0098 | D4: PROD-053 | E4: R014 | F4: 8 | G4: 470 | H4: 3.3 | I4: 3635.92 | J4: Pending | K4: Delhi
A5: ORD-00004 | B5: 45413 | C5: CUST-0071 | D5: PROD-028 | E5: R006 | F5: 1 | G5: 3660 | H5: 15.7 | I5: 3085.38 | J5: Completed | K5: Delhi
A6: ORD-00005 | B6: 45611 | C6: CUST-0180 | D6: PROD-012 | E6: R008 | F6: 1 | G6: 3160 | H6: 26 | I6: 2338.4 | J6: Completed | K6: Chennai
A7: ORD-00006 | B7: 45406 | C7: CUST-0275 | D7: PROD-032 | E7: R025 | F7: 4 | G7: 370 | H7: 29 | I7: 1050.8 | J7: Completed | K7: Mumbai
A8: ORD-00007 | B8: 45455 | C8: CUST-0293 | D8: PROD-057 | E8: R024 | F8: 3 | G8: 960 | H8: 5.8 | I8: 2712.96 | J8: Completed | K8: Bengaluru
A9: ORD-00008 | B9: 45617 | C9: CUST-0281 | D9: PROD-007 | E9: R019 | F9: 8 | G9: 1430 | H9: 2.4 | I9: 11165.44 | J9: Completed | K9: Bengaluru
A10: ORD-00009 | B10: 45549 | C10: CUST-0260 | D10: PROD-038 | E10: R008 | F10: 3 | G10: 5490 | H10: 14.2 | I10: 14131.26 | J10: Completed | K10: Bengaluru
A11: ORD-00010 | B11: 45396 | C11: CUST-0147 | D11: PROD-030 | E11: R028 | F11: 3 | G11: 970 | H11: 1.2 | I11: 2875.08 | J11: Completed | K11: Pune
A12: ORD-00011 | B12: 45560 | C12: CUST-0204 | D12: PROD-024 | E12: R010 | F12: 7 | G12: 2270 | H12: 7.1 | I12: 14761.81 | J12: Pending | K12: Hyderabad
A13: ORD-00012 | B13: 45332 | C13: CUST-0147 | D13: PROD-010 | E13: R024 | F13: 9 | G13: 2640 | H13: 21.7 | I13: 18604.08 | J13: Completed | K13: Pune
... A2001: ORD-02000 | B2001: 45325 | C2001: CUST-0238 | D2001: PROD-034 | E2001: R023 | F2001: 6 | G2001: 5080 | H2001: 28.1 | I2001: 21915.12 | J2001: Completed | K2001: Delhi

Sheet Customers
A1: customer_id | B1: customer_name | C1: age | D1: city | E1: segment | F1: signup_date
A2: CUST-0001 | B2: Amit Agarwal | C2: 36 | D2: Pune | E2: Retail | F2: 44819
A3: CUST-0002 | B3: Vihaan Malhotra | C3: 42 | D3: Pune | E3: Corporate | F3: 44984
A4: CUST-0003 | B4: Navya Malhotra | C4: 33 | D4: Mumbai | E4: Retail | F4: 44059
A5: CUST-0004 | B5: Aaradhya Mehta | C5: 53 | D5: delhi | E5: Retail | F5: 44054
A6: CUST-0005 | B6: Myra Malhotra | C6: 52 | D6: Chennai | E6: Corporate | F6: 45037
A7: CUST-0006 | B7: Shaurya Iyer | C7: 44 | D7: Pune | E7: SMB | F7: 44302
A8: CUST-0007 | B8: Dhruv Joshi | C8: 47 | D8: Bengaluru | E8: Retail | F8: 44498
A9: CUST-0008 | B9: Kavita Malhotra | C9: 39 | D9: Pune | E9: SMB | F9: 45162
A10: CUST-0009 | B10: Neha Malhotra | C10: 61 | D10: Mumbai | E10: Retail | F10: 44343
A11: CUST-0010 | B11: Aaradhya Gupta | C11: 61 | D11: Mumbai | E11: SMB | F11: 44975
A12: CUST-0011 | B12: Diya Menon | C12: 41 | D12: Chennai | E12: Corporate | F12: 44821
A13: CUST-0012 | B13: Prisha Desai | C13: 43 | D13: Pune | E13: Retail | F13: 44718
... A301: CUST-0300 | B301: Rohit Nair | C301: 38 | D301: Mumbai | E301: Retail | F301: 43932

Sheet Products
A1: product_id | B1: product_name | C1: category | D1: unit_cost | E1: unit_price | F1: is_active
A2: PROD-001 | B2: Smartphone Pro | C2: Electronics | D2: 2405 | E2: 5330 | F2: TRUE
A3: PROD-002 | B3: Wireless Earbuds | C3: Electronics | D3: 1052 | E3: 2600 | F3: TRUE
A4: PROD-003 | B4: Smart Watch | C4: Electronics | D4: 1665 | E4: 3570 | F4: TRUE
A5: PROD-004 | B5: Laptop Bag | C5: Electronics | D5: 1559 | E5: 3870 | F5: TRUE
A6: PROD-005 | B6: Power Bank | C6: Electronics | D6: 128 | E6: 300 | F6: TRUE
A7: PROD-006 | B7: Bluetooth Speaker | C7: Electronics | D7: 2865 | E7: 3970 | F7: TRUE
A8: PROD-007 | B8: USB-C Cable | C8: Electronics | D8: 861 | E8: 1430 | F8: TRUE
A9: PROD-008 | B9: Wireless Mouse | C9: Electronics | D9: 1259 | E9: 2660 | F9: FALSE
A10: PROD-009 | B10: Mechanical Keyboard | C10: Electronics | D10: 517 | E10: 1220 | F10: TRUE
A11: PROD-010 | B11: Tablet Stand | C11: Electronics | D11: 1149 | E11: 2640 | F11: TRUE
A12: PROD-011 | B12: Cotton T-Shirt | C12: Apparel | D12: 1748 | E12: 3450 | F12: TRUE
A13: PROD-012 | B13: Denim Jeans | C13: Apparel | D13: 1886 | E13: 3160 | F13: TRUE
... A61: PROD-060 | B61: Gym Gloves | C61: Sports | D61: 147 | E61: 190 | F61: TRUE

Sheet Sales_Reps
A1: rep_id | B1: rep_name | C1: region | D1: hire_date | E1: team_lead_id
A2: R001 | B2: Rajesh Malhotra | C2: North | D2: 44207
A3: R002 | B3: Sunita Malhotra | C3: North | D3: 44028
A4: R003 | B4: Amit Singh | C4: North | D4: 43651
A5: R004 | B5: Priya Singh | C5: North | D5: 44907
A6: R005 | B6: Vikram Patel | C6: North | D6: 43588 | E6: R001
A7: R006 | B7: Neha Desai | C7: North | D7: 44131 | E7: R001
A8: R007 | B8: Suresh Menon | C8: North | D8: 43493 | E8: R001
A9: R008 | B9: Kavita Patel | C9: North | D9: 44693 | E9: R001
A10: R009 | B10: Manoj Patel | C10: South | D10: 44804 | E10: R002
A11: R010 | B11: Divya Rao | C11: South | D11: 43904 | E11: R002
A12: R011 | B12: Anil Verma | C12: South | D12: 44622 | E12: R002
A13: R012 | B13: Pooja Nair | C13: South | D13: 44890 | E13: R002
A14: R013 | B14: Sanjay Kapoor | C14: South | D14: 45215 | E14: R002
A15: R014 | B15: Ritu Menon | C15: South | D15: 44469 | E15: R002
A16: R015 | B16: Deepak Shah | C16: South | D16: 45231 | E16: R002
A17: R016 | B17: Anjali Chopra | C17: South | D17: 43614 | E17: R002
... A31: R030 | B31: Kiran Bhatt | C31: West | D31: 44506 | E31: R004

Sheet Targets
A1: rep_id | B1: Jan-24 | C1: Feb-24 | D1: Mar-24 | E1: Apr-24 | F1: May-24 | G1: Jun-24 | H1: Jul-24 | I1: Aug-24 | J1: Sep-24 | K1: Oct-24 | L1: Nov-24 | M1: Dec-24
A2: R001 | B2: 231324 | C2: 171682 | D2: 234376 | E2: 326967 | F2: 350588 | G2: 385324 | H2: 307980 | I2: 327947 | J2: 181016 | K2: 374039 | L2: 212805 | M2: 405999
A3: R002 | B3: 438126 | C3: 346266 | D3: 329993 | E3: 370744 | F3: 294660 | G3: 341556 | H3: 151934 | I3: 223794 | J3: 438641 | K3: 344308 | L3: 296172 | M3: 304288
A4: R003 | B4: 358703 | C4: 320519 | D4: 327321 | E4: 298753 | F4: 254636 | G4: 351929 | H4: 264723 | I4: 216459 | J4: 391945 | K4: 362426 | L4: 289199 | M4: 301863
A5: R004 | B5: 389594 | C5: 376422 | D5: 324156 | E5: 420255 | F5: 409107 | G5: 269954 | H5: 179097 | I5: 370568 | J5: 387395 | K5: 243454 | L5: 232530 | M5: 201999
A6: R005 | B6: 436862 | C6: 391158 | D6: 340224 | E6: 170548 | F6: 229390 | G6: 349525 | H6: 154683 | I6: 320848 | J6: 354452 | K6: 377180 | L6: 342347 | M6: 183362
A7: R006 | B7: 348734 | C7: 358191 | D7: 250385 | E7: 219657 | F7: 249365 | G7: 435704 | H7: 260892 | I7: 250741 | J7: 358402 | K7: 379858 | L7: 213280 | M7: 224634
A8: R007 | B8: 280057 | C8: 330342 | D8: 336856 | E8: 227425 | F8: 233647 | G8: 307088 | H8: 370724 | I8: 440008 | J8: 406347 | K8: 217357 | L8: 299289 | M8: 214568
A9: R008 | B9: 252886 | C9: 206057 | D9: 318209 | E9: 411230 | F9: 448660 | G9: 171135 | H9: 305339 | I9: 432264 | J9: 294273 | K9: 371409 | L9: 284207 | M9: 437068
A10: R009 | B10: 268752 | C10: 393256 | D10: 310649 | E10: 246237 | F10: 271287 | G10: 314545 | H10: 406506 | I10: 334930 | J10: 348625 | K10: 408928 | L10: 243749 | M10: 418409
A11: R010 | B11: 384734 | C11: 156698 | D11: 283679 | E11: 276085 | F11: 409270 | G11: 285230 | H11: 304233 | I11: 178221 | J11: 284216 | K11: 287373 | L11: 229082 | M11: 298969
A12: R011 | B12: 186029 | C12: 151419 | D12: 253251 | E12: 379757 | F12: 204209 | G12: 179396 | H12: 378008 | I12: 182649 | J12: 267772 | K12: 350352 | L12: 358042 | M12: 359960
A13: R012 | B13: 352158 | C13: 251181 | D13: 321255 | E13: 300863 | F13: 241731 | G13: 393275 | H13: 313561 | I13: 283604 | J13: 429065 | K13: 194420 | L13: 254168 | M13: 389283
... A31: R030 | B31: 151584 | C31: 221679 | D31: 385157 | E31: 290386 | F31: 236041 | G31: 407985 | H31: 184446 | I31: 342894 | J31: 180344 | K31: 292917 | L31: 314858 | M31: 364057

Sheet Q1_Lookups
A1: Q1 - LOOKUP FUNCTIONS (25 marks total)
A2: VLOOKUP · INDEX-MATCH · Two-way lookup · Chain lookup · Approximate lookup · Self-join
A4: Q# | B4: Question | C4: Marks | D4: Hint | E4: Your Answer | F4: Format
A5: Q1.1 | B5: For order ORD-00234, what is the customer_id? | C5: 3 | D5: Simple VLOOKUP on Orders sheet. | E5: =Calculations!$U$2 -> CUST-0173 | F5: CUST-####
A6: Q1.2 | B6: For order ORD-00456, what is the product_name? (You will need to look up the product_id first, then find its name in Products.) | C6: 3 | D6: Two-step lookup, or nested VLOOKUP. | E6: =Calculations!$U$3 -> Dumbbells 5kg | F6: Text
A7: Q1.3 | B7: For order ORD-00987, what is the rep_name of the sales rep? Note: the rep_name is in a column that appears to the LEFT of what you might look up first. | C7: 3 | D7: VLOOKUP has directional limits - INDEX/MATCH does not. | E7: =Calculations!$U$4 -> Nisha Menon | F7: Text
A8: Q1.4 | B8: From the Targets sheet, what is the target value for rep R012 in the month Mar-24? | C8: 4 | D8: Two-way lookup: row = rep_id, column = month. | E8: =Calculations!$U$5 -> 321255 | F8: Whole number
A9: Q1.5 | B9: For order ORD-01500, what is the CATEGORY of the product ordered? (Chain: order → product_id → category) | C9: 4 | D9: Multi-hop lookup across sheets. | E9: =Calculations!$U$6 -> Electronics | F9: Text
A10: Q1.6 | B10: For order ORD-00789, which DISCOUNT SLAB does it fall in? Use the slab table below (rows 20-24). Slab breakpoints are the LOWER bound of each range. | C10: 3 | D10: Approximate-match VLOOKUP (sort ascending, TRUE / omit last arg). | E10: =Calculations!$U$7 -> Bronze | F10: Text
A11: Q1.7 | B11: For order ORD-01234, in one cell produce the string: "<rep_name> (<sales_region>)" - e.g. "Amit Singh (South)". | C11: 3 | D11: Two lookups joined with & or CONCATENATE. | E11: =Calculations!$U$8 -> Sanjay Kapoor (South) | F11: Text
A12: Q1.8 | B12: What is the rep_name of the TEAM LEAD for rep R017? (The Sales_Reps sheet has team_lead_id - you need to self-join to find that person's name.) | C12: 2 | D12: Look up the team_lead_id, then look up THAT id's rep_name. | E12: =Calculations!$U$9 -> Amit Singh | F12: Text
B15: DISCOUNT SLAB REFERENCE TABLE (use for Q1.6)
B17: Discount % (Lower) | C17: Slab
B18: 0 | C18: Bronze
B19: 5 | C19: Silver
B20: 15 | C20: Gold
B21: 25 | C21: Platinum

Sheet Q2_Cleaning
A1: Q2 - DATA CLEANING & QUALITY DIAGNOSTICS (20 marks total)
A2: Duplicates · Whitespace · Case Inconsistency · Referential Integrity · Discontinued SKUs · Anomaly Patterns
A4: Q# | B4: Question | C4: Marks | D4: Hint | E4: Your Answer | F4: Format
A5: Q2.1 | B5: How many DUPLICATE rows exist in the Orders sheet (i.e., how many order_id values appear more than once)? Count each duplicate as ONE (not the extras). | C5: 3 | D5: COUNTIF > 1, then count. Watch what you're counting - rows or IDs. | E5: =Calculations!$U$10 -> 20 | F5: Whole number
A6: Q2.2 | B6: How many customers in the Customers sheet have LEADING or TRAILING whitespace in their customer_name? | C6: 3 | D6: Compare LEN vs LEN(TRIM). Or use SUMPRODUCT with a boolean. | E6: =Calculations!$U$11 -> 15 | F6: Whole number
A7: Q2.3 | B7: The Customers sheet has some cities in inconsistent case (e.g., "mumbai", "MUMBAI", "Mumbai"). How many DISTINCT cities exist AFTER standardizing case? | C7: 3 | D7: Combine PROPER/UPPER with a de-dup count. SUMPRODUCT + 1/COUNTIF trick works. | E7: =Calculations!$U$12 -> 6 | F7: Whole number
A8: Q2.4 | B8: How many orders reference a customer_id that DOES NOT EXIST in the Customers sheet? (Broken foreign key) | C8: 4 | D8: Use MATCH with ISNA/ISERROR, then count. | E8: =Calculations!$U$13 -> 30 | F8: Whole number
A9: Q2.5 | B9: How many orders reference a product that is currently DISCONTINUED (is_active = FALSE in the Products sheet)? | C9: 3 | D9: VLOOKUP the is_active flag, then count where FALSE. | E9: =Calculations!$U$14 -> 174 | F9: Whole number
A10: Q2.6 | B10: Find the "suspicious pattern": how many orders have payment_status = "Cancelled" AND a discount_pct > 20%? (This pattern often indicates promo abuse - a real-world diagnostic query.) | C10: 4 | D10: COUNTIFS with two criteria. | E10: =Calculations!$U$15 -> 58 | F10: Whole number

Sheet Q3_Aggregation
A1: Q3 - CONDITIONAL AGGREGATION (25 marks total)
A2: SUMIFS · COUNTIFS · AVERAGEIFS · Nested IF logic · Multi-sheet aggregation · Top-N logic
A4: Q# | B4: Question | C4: Marks | D4: Hint | E4: Your Answer | F4: Format
A5: Q3.1 | B5: What is the TOTAL REVENUE (sum of final_amount) for orders in Q3 2024 (Jul-Sep) where ship_city is Mumbai? | C5: 4 | D5: SUMIFS with 3 conditions: date >= start, date <= end, city = Mumbai. Beware case issues. | E5: =Calculations!$U$16 -> 1217239 | F5: Currency
A6: Q3.2 | B6: How many orders have discount_pct > 15% AND payment_status = "Completed"? | C6: 3 | D6: COUNTIFS with two conditions. | E6: =Calculations!$U$17 -> 723 | F6: Whole number
A7: Q3.3 | B7: What is the AVERAGE final_amount for orders where the product CATEGORY is "Electronics" AND the customer SEGMENT is "Corporate"? Note: Both fields come from OTHER sheets - you'll need helper columns. | C7: 5 | D7: Helper columns in Orders: VLOOKUP category from Products, VLOOKUP segment from Customers. Then AVERAGEIFS. | E7: =Calculations!$U$18 -> 13981.402 | F7: Currency
A8: Q3.4 | B8: What is the COMBINED REVENUE of the TOP 3 reps by total revenue? (Sum of the 3 highest rep totals.) | C8: 4 | D8: Compute per-rep totals, then use SUMPRODUCT with LARGE, or sort and sum top 3. | E8: =Calculations!$U$19 -> 3342678.5 | F8: Currency
A9: Q3.5 | B9: For rep R015 in Nov-24: compute the actual revenue and compare to the target (from Targets sheet). Report the PERFORMANCE TIER using: <80% → "Below", 80-120% → "On Track", >120% → "Exceeds". Return only the tier text. | C9: 5 | D9: Nested IF (or IFS): compute actual/target ratio, then classify. | E9: =Calculations!$U$20 -> Below | F9: Text
A10: Q3.6 | B10: What is the TOTAL revenue from Corporate segment customers aged between 30 and 40 (both inclusive)? | C10: 4 | D10: Helper columns for age and segment. Then SUMIFS with numeric range. | E10: =Calculations!$U$21 -> 982568.4 | F10: Currency

Sheet Q4_Pivot
A1: Q4 - PIVOT TABLES (20 marks total)
A2: 2D Pivots · Filters · % of Row Total · Date Grouping · Calculated Fields · Cross-Sheet Data
A4: Q# | B4: Question | C4: Marks | D4: Hint | E4: Your Answer | F4: Format
A5: Q4.1 | B5: Build a pivot with sales_region as rows and product category as columns, values = SUM of final_amount. What value appears at the intersection of "South" and "Electronics"? | C5: 4 | D5: You need to add category (from Products) and region (from Sales_Reps) as columns to Orders first. Insert PivotTable from combined data. | E5: =Calculations!$U$22 -> 1314107.4 | F5: Currency
A6: Q4.2 | B6: Build a pivot: rows = order month (Jan-24 through Dec-24), columns = sales_rep_id, values = SUM of final_amount. What is the HIGHEST single value in the entire pivot? (One number.) | C6: 4 | D6: After building, use MAX() over the pivot data range, or scan visually. | E6: =Calculations!$U$23 -> 216421.52 | F6: Currency
A7: Q4.3 | B7: For the North sales_region only: what PERCENTAGE of total revenue comes from the Apparel category? Configure the pivot with Show Values As → % of Row Total. | C7: 4 | D7: Pivot: rows=region, cols=category, values=sum(final_amount), Show Values As = % of Row Total. | E7: =Calculations!$U$24 -> 0.1402315 | F7: Percentage
A8: Q4.4 | B8: Group order dates by QUARTER in a pivot. What is the total revenue for Q4 2024 (Oct-Dec)? | C8: 4 | D8: PivotTable → Group By → Quarter. Or SUMIFS with date range. | E8: =Calculations!$U$25 -> 6459443 | F8: Currency
A9: Q4.5 | B9: Create a CALCULATED FIELD in the pivot: profit_margin = (unit_price - unit_cost) / unit_price. What is the AVERAGE profit_margin for orders shipped to Delhi? Give as a percentage. | C9: 4 | D9: Add unit_cost via VLOOKUP as helper column. Create pivot calculated field, filter to Delhi. | E9: =Calculations!$U$26 -> 0.44880873 | F9: Percentage

Sheet Q5_Advanced
A1: Q5 - ADVANCED (10 marks total)
A2: RANK · Running Totals · TEXTJOIN · LARGE + INDEX/MATCH · Multi-condition top-N
A4: Q# | B4: Question | C4: Marks | D4: Hint | E4: Your Answer | F4: Format
A5: Q5.1 | B5: Rank all sales reps by total revenue (highest = rank 1). Who (name) is at RANK #7? | C5: 2 | D5: Per-rep totals, then use RANK.EQ, or sort. Return the rep_name at position 7. | E5: =Calculations!$U$27 -> #N/A | F5: Text
A6: Q5.2 | B6: What is the CUMULATIVE revenue from Jan 2024 through the end of Aug 2024? (Sum of final_amount where order_date <= 31-Aug-2024.) | C6: 2 | D6: SUMIFS with date <=. | E6: =Calculations!$U$28 -> 18050690 | F6: Currency
A7: Q5.3 | B7: Among orders where the sales rep is in the WEST region: which product (by name) has the 2nd highest total revenue? | C7: 3 | D7: Helper: sales_region on orders. Filter/pivot to West, sum by product, rank, get #2, VLOOKUP product name. | E7: =Calculations!$U$29 -> #N/A | F7: Text
A8: Q5.4 | B8: Concatenate the names of the top 5 reps by revenue into a single cell, separated by " | " (space-pipe-space). | C8: 2 | D8: TEXTJOIN with delimiter " | ". Combine with LARGE to pull top 5. | E8: =Calculations!$U$30 -> #NAME? | F8: Text
A9: Q5.5 | B9: What is the HIGHEST single order value (final_amount) where ship_city = "Bengaluru" AND the product's category = "Grocery"? | C9: 1 | D9: MAXIFS with a category helper column, or nested MAX(IF()). | E9: =Calculations!$U$31 -> #NAME? | F9: Currency

Sheet Calculations
A1: Order ID | B1: Order Date | C1: Customer ID | D1: Product ID | E1: Sales Rep ID | F1: Quantity | G1: Unit Price | H1: Discount % | I1: Final Amount | J1: Payment Status | K1: Ship City | L1: Category | M1: Unit Cost | N1: Sales Region | O1: Customer Segment | P1: Customer Age | Q1: Profit Margin | R1: Customer Check | S1: Active Product? | T1: Question | U1: Answer / Calculation | V1: Beginner formula used | W1: Rep ID | X1: Rep Name | Y1: Total Revenue | Z1: Rank | AB1: Month | AC1: R001 | AD1: R002 | AE1: R003 | AF1: R004 | AG1: R005 | AH1: R006 | AI1: R007 | AJ1: R008 | AK1: R009 | AL1: R010 | AM1: R011 | AN1: R012 | AO1: R013 | AP1: R014 | AQ1: R015 | AR1: R016 | AS1: R017 | AT1: R018 | AU1: R019 | AV1: R020 | AW1: R021 | AX1: R022 | AY1: R023 | AZ1: R024 | BA1: R025 | BB1: R026 | BC1: R027 | BD1: R028 | BE1: R029 | BF1: R030 | BH1: Product ID | BI1: Product Name | BJ1: West Revenue | BK1: West Rank | BL1: Duplicate Share | BM1: Name Has Extra Space | BN1: City Unique Share | BO1: Missing Customer | BP1: Inactive Product
A2: =Orders!A2 -> ORD-00001 | B2: =Orders!B2 -> 45549 | C2: =Orders!C2 -> CUST-0243 | D2: =Orders!D2 -> PROD-014 | E2: =Orders!E2 -> R007 | F2: =Orders!F2 -> 8 | G2: =Orders!G2 -> 3620 | H2: =Orders!H2 -> 15.4 | ... K2: =Orders!K2 -> Pune | L2: =IFERROR(VLOOKUP(D2,Products!$A$2:$F$61,3,FALSE),"") -> Apparel | M2: =IFERROR(VLOOKUP(D2,Products!$A$2:$F$61,4,FALSE),"") -> 2509 | N2: =IFERROR(VLOOKUP(E2,Sales_Reps!$A$2:$E$31,3,FALSE),"") -> North | O2: =IFERROR(VLOOKUP(C2,Customers!$A$2:$F$301,5,FALSE),"") -> SMB | P2: =IFERROR(VLOOKUP(C2,Customers!$A$2:$F$301,3,FALSE),"") -> 44 | Q2: =IFERROR((G2-M2)/G2,0) -> 0.30690608 | R2: =IFERROR(VLOOKUP(C2,Customers!$A$2:$F$301,1,FALSE),"") -> CUST-0243 | S2: =IFERROR(VLOOKUP(D2,Products!$A$2:$F$61,6,FALSE),"") -> TRUE | T2: Q1.1 | U2: =INDEX($C$2:$C$2001,MATCH("ORD-00234",$A$2:$A$2001,0)) -> CUST-0173 | V2: INDEX + MATCH | W2: =Sales_Reps!A2 -> R001 | X2: =Sales_Reps!B2 -> Rajesh Malhotra | Y2: =SUMIF($E$2:$E$2001,W2,$I$2:$I$2001) -> 789849.6 | Z2: =_xludf.RANK.EQ(Y2,$Y$2:$Y$31,0) -> #NAME? | AB2: =DATE(2024,1,1) -> 45292 | AC2: =SUMIFS($I$2:$I$2001,$B$2:$B$2001,">="&$AB2,$B$2:$B$2001,"<"&EDATE($AB2,1),$E$2:$E$2001,AC$1) -> 43650.56 | AD2: =SUMIFS($I$2:$I$2001,$B$2:$B$2001,">="&$AB2,$B$2:$B$2001,"<"&EDATE($AB2,1),$E$2:$E$2001,AD$1) -> 51707.32 | AE2: =SUMIFS($I$2:$I$2001,$B$2:$B$2001,">="&$AB2,$B$2:$B$2001,"<"&EDATE($AB2,1),$E$2:$E$2001,AE$1) -> 54307 | AF2: =SUMIFS($I$2:$I$2001,$B$2:$B$2001,">="&$AB2,$B$2:$B$2001,"<"&EDATE($AB2,1),$E$2:$E$2001,AF$1) -> 57892.11 | AG2: =SUMIFS($I$2:$I$2001,$B$2:$B$2001,">="&$AB2,$B$2:$B$2001,"<"&EDATE($AB2,1),$E$2:$E$2001,AG$1) -> 70665.51 | AH2: =SUMIFS($I$2:$I$2001,$B$2:$B$2001,">="&$AB2,$B$2:$B$2001,"<"&EDATE($AB2,1),$E$2:$E$2001,AH$1) -> 84968.56 | AI2: =SUMIFS($I$2:$I$2001,$B$2:$B$2001,">="&$AB2,$B$2:$B$2001,"<"&EDATE($AB2,1),$E$2:$E$2001,AI$1) -> 92029.91 | AJ2: =SUMIFS($I$2:$I$2001,$B$2:$B$2001,">="&$AB2,$B$2:$B$2001,"<"&EDATE($AB2,1),$E$2:$E$2001,AJ$1) -> 61557.02 | ... BF2: =SUMIFS($I$2:$I$2001,$B$2:$B$2001,">="&$AB2,$B$2:$B$2001,"<"&EDATE($AB2,1),$E$2:$E$2001,BF$1) -> 59170.81 | BH2: =Products!A2 -> PROD-001 | BI2: =Products!B2 -> Smartphone Pro | BJ2: =SUMIFS($I$2:$I$2001,$N$2:$N$2001,"West",$D$2:$D$2001,BH2) -> 155358.84 | BK2: =_xludf.RANK.EQ(BJ2,$BJ$2:$BJ$61,0) -> #NAME? | BL2: 0 | BM2: 0 | BN2: 0.018867925 | BO2: 0 | BP2: 0
A3: =Orders!A3 -> ORD-00002 | B3: =Orders!B3 -> 45340 | C3: =Orders!C3 -> CUST-0202 | D3: =Orders!D3 -> PROD-020 | E3: =Orders!E3 -> R005 | F3: =Orders!F3 -> 2 | G3: =Orders!G3 -> 820 | H3: =Orders!H3 -> 10.8 | ... K3: =Orders!K3 -> Chennai | L3: =IFERROR(VLOOKUP(D3,Products!$A$2:$F$61,3,FALSE),"") -> Apparel | M3: =IFERROR(VLOOKUP(D3,Products!$A$2:$F$61,4,FALSE),"") -> 391 | N3: =IFERROR(VLOOKUP(E3,Sales_Reps!$A$2:$E$31,3,FALSE),"") -> North | O3: =IFERROR(VLOOKUP(C3,Customers!$A$2:$F$301,5,FALSE),"") -> Retail | P3: =IFERROR(VLOOKUP(C3,Customers!$A$2:$F$301,3,FALSE),"") -> 39 | Q3: =IFERROR((G3-M3)/G3,0) -> 0.52317073 | R3: =IFERROR(VLOOKUP(C3,Customers!$A$2:$F$301,1,FALSE),"") -> CUST-0202 | S3: =IFERROR(VLOOKUP(D3,Products!$A$2:$F$61,6,FALSE),"") -> TRUE | T3: Q1.2 | U3: =VLOOKUP(INDEX($D$2:$D$2001,MATCH("ORD-00456",$A$2:$A$2001,0)),Products!$A$2:$F$61,2,FALSE) -> Dumbbells 5kg | V3: Order product ID, then VLOOKUP | W3: =Sales_Reps!A3 -> R002 | X3: =Sales_Reps!B3 -> Sunita Malhotra | Y3: =SUMIF($E$2:$E$2001,W3,$I$2:$I$2001) -> 980063.66 | Z3: =_xludf.RANK.EQ(Y3,$Y$2:$Y$31,0) -> #NAME? | AB3: =DATE(2024,2,1) -> 45323 | AC3: =SUMIFS($I$2:$I$2001,$B$2:$B$2001,">="&$AB3,$B$2:$B$2001,"<"&EDATE($AB3,1),$E$2:$E$2001,AC$1) -> 127005.17 | AD3: =SUMIFS($I$2:$I$2001,$B$2:$B$2001,">="&$AB3,$B$2:$B$2001,"<"&EDATE($AB3,1),$E$2:$E$2001,AD$1) -> 125187.78 | AE3: =SUMIFS($I$2:$I$2001,$B$2:$B$2001,">="&$AB3,$B$2:$B$2001,"<"&EDATE($AB3,1),$E$2:$E$2001,AE$1) -> 32452 | AF3: =SUMIFS($I$2:$I$2001,$B$2:$B$2001,">="&$AB3,$B$2:$B$2001,"<"&EDATE($AB3,1),$E$2:$E$2001,AF$1) -> 58818.56 | AG3: =SUMIFS($I$2:$I$2001,$B$2:$B$2001,">="&$AB3,$B$2:$B$2001,"<"&EDATE($AB3,1),$E$2:$E$2001,AG$1) -> 57914.81 | AH3: =SUMIFS($I$2:$I$2001,$B$2:$B$2001,">="&$AB3,$B$2:$B$2001,"<"&EDATE($AB3,1),$E$2:$E$2001,AH$1) -> 34581.99 | AI3: =SUMIFS($I$2:$I$2001,$B$2:$B$2001,">="&$AB3,$B$2:$B$2001,"<"&EDATE($AB3,1),$E$2:$E$2001,AI$1) -> 130276.04 | AJ3: =SUMIFS($I$2:$I$2001,$B$2:$B$2001,">="&$AB3,$B$2:$B$2001,"<"&EDATE($AB3,1),$E$2:$E$2001,AJ$1) -> 23463.3 | ... BF3: =SUMIFS($I$2:$I$2001,$B$2:$B$2001,">="&$AB3,$B$2:$B$2001,"<"&EDATE($AB3,1),$E$2:$E$2001,BF$1) -> 17274.29 | BH3: =Products!A3 -> PROD-002 | BI3: =Products!B3 -> Wireless Earbuds | BJ3: =SUMIFS($I$2:$I$2001,$N$2:$N$2001,"West",$D$2:$D$2001,BH3) -> 105284.4 | BK3: =_xludf.RANK.EQ(BJ3,$BJ$2:$BJ$61,0) -> #NAME? | BL3: 0 | BM3: 0 | BN3: 0.018867925 | BO3: 0 | BP3: 0
A4: =Orders!A4 -> ORD-00003 | B4: =Orders!B4 -> 45371 | C4: =Orders!C4 -> CUST-0098 | D4: =Orders!D4 -> PROD-053 | E4: =Orders!E4 -> R014 | F4: =Orders!F4 -> 8 | G4: =Orders!G4 -> 470 | H4: =Orders!H4 -> 3.3 | ... K4: =Orders!K4 -> Delhi | L4: =IFERROR(VLOOKUP(D4,Products!$A$2:$F$61,3,FALSE),"") -> Sports | M4: =IFERROR(VLOOKUP(D4,Products!$A$2:$F$61,4,FALSE),"") -> 302 | N4: =IFERROR(VLOOKUP(E4,Sales_Reps!$A$2:$E$31,3,FALSE),"") -> South | O4: =IFERROR(VLOOKUP(C4,Customers!$A$2:$F$301,5,FALSE),"") -> Retail | P4: =IFERROR(VLOOKUP(C4,Customers!$A$2:$F$301,3,FALSE),"") -> 52 | Q4: =IFERROR((G4-M4)/G4,0) -> 0.35744681 | R4: =IFERROR(VLOOKUP(C4,Customers!$A$2:$F$301,1,FALSE),"") -> CUST-0098 | S4: =IFERROR(VLOOKUP(D4,Products!$A$2:$F$61,6,FALSE),"") -> FALSE | T4: Q1.3 | U4: =INDEX(Sales_Reps!$B$2:$B$31,MATCH(INDEX($E$2:$E$2001,MATCH("ORD-00987",$A$2:$A$2001,0)),Sales_Reps!$A$2:$A$31,0)) -> Nisha Menon | V4: INDEX + MATCH for rep name | W4: =Sales_Reps!A4 -> R003 | X4: =Sales_Reps!B4 -> Amit Singh | Y4: =SUMIF($E$2:$E$2001,W4,$I$2:$I$2001) -> 986692.91 | Z4: =_xludf.RANK.EQ(Y4,$Y$2:$Y$31,0) -> #NAME? | AB4: =DATE(2024,3,1) -> 45352 | AC4: =SUMIFS($I$2:$I$2001,$B$2:$B$2001,">="&$AB4,$B$2:$B$2001,"<"&EDATE($AB4,1),$E$2:$E$2001,AC$1) -> 58208.49 | AD4: =SUMIFS($I$2:$I$2001,$B$2:$B$2001,">="&$AB4,$B$2:$B$2001,"<"&EDATE($AB4,1),$E$2:$E$2001,AD$1) -> 53533 | AE4: =SUMIFS($I$2:$I$2001,$B$2:$B$2001,">="&$AB4,$B$2:$B$2001,"<"&EDATE($AB4,1),$E$2:$E$2001,AE$1) -> 107489.23 | AF4: =SUMIFS($I$2:$I$2001,$B$2:$B$2001,">="&$AB4,$B$2:$B$2001,"<"&EDATE($AB4,1),$E$2:$E$2001,AF$1) -> 14394.38 | AG4: =SUMIFS($I$2:$I$2001,$B$2:$B$2001,">="&$AB4,$B$2:$B$2001,"<"&EDATE($AB4,1),$E$2:$E$2001,AG$1) -> 85853.43 | AH4: =SUMIFS($I$2:$I$2001,$B$2:$B$2001,">="&$AB4,$B$2:$B$2001,"<"&EDATE($AB4,1),$E$2:$E$2001,AH$1) -> 145435.13 | AI4: =SUMIFS($I$2:$I$2001,$B$2:$B$2001,">="&$AB4,$B$2:$B$2001,"<"&EDATE($AB4,1),$E$2:$E$2001,AI$1) -> 105489.83 | AJ4: =SUMIFS($I$2:$I$2001,$B$2:$B$2001,">="&$AB4,$B$2:$B$2001,"<"&EDATE($AB4,1),$E$2:$E$2001,AJ$1) -> 164615.05 | ... BF4: =SUMIFS($I$2:$I$2001,$B$2:$B$2001,">="&$AB4,$B$2:$B$2001,"<"&EDATE($AB4,1),$E$2:$E$2001,BF$1) -> 122041.06 | BH4: =Products!A4 -> PROD-003 | BI4: =Products!B4 -> Smart Watch | BJ4: =SUMIFS($I$2:$I$2001,$N$2:$N$2001,"West",$D$2:$D$2001,BH4) -> 248025.75 | BK4: =_xludf.RANK.EQ(BJ4,$BJ$2:$BJ$61,0) -> #NAME? | BL4: 0 | BM4: 0 | BN4: 0.018518519 | BO4: 0 | BP4: 1
A5: =Orders!A5 -> ORD-00004 | B5: =Orders!B5 -> 45413 | C5: =Orders!C5 -> CUST-0071 | D5: =Orders!D5 -> PROD-028 | E5: =Orders!E5 -> R006 | F5: =Orders!F5 -> 1 | G5: =Orders!G5 -> 3660 | H5: =Orders!H5 -> 15.7 | ... K5: =Orders!K5 -> Delhi | L5: =IFERROR(VLOOKUP(D5,Products!$A$2:$F$61,3,FALSE),"") -> Grocery | M5: =IFERROR(VLOOKUP(D5,Products!$A$2:$F$61,4,FALSE),"") -> 2214 | N5: =IFERROR(VLOOKUP(E5,Sales_Reps!$A$2:$E$31,3,FALSE),"") -> North | O5: =IFERROR(VLOOKUP(C5,Customers!$A$2:$F$301,5,FALSE),"") -> Corporate | P5: =IFERROR(VLOOKUP(C5,Customers!$A$2:$F$301,3,FALSE),"") -> 46 | Q5: =IFERROR((G5-M5)/G5,0) -> 0.39508197 | R5: =IFERROR(VLOOKUP(C5,Customers!$A$2:$F$301,1,FALSE),"") -> CUST-0071 | S5: =IFERROR(VLOOKUP(D5,Products!$A$2:$F$61,6,FALSE),"") -> FALSE | T5: Q1.4 | U5: =INDEX(Targets!$A$2:$M$31,MATCH("R012",Targets!$A$2:$A$31,0),MATCH("Mar-24",Targets!$A$1:$M$1,0)) -> 321255 | V5: Two-way INDEX + MATCH | W5: =Sales_Reps!A5 -> R004 | X5: =Sales_Reps!B5 -> Priya Singh | Y5: =SUMIF($E$2:$E$2001,W5,$I$2:$I$2001) -> 589026.29 | Z5: =_xludf.RANK.EQ(Y5,$Y$2:$Y$31,0) -> #NAME? | AB5: =DATE(2024,4,1) -> 45383 | AC5: =SUMIFS($I$2:$I$2001,$B$2:$B$2001,">="&$AB5,$B$2:$B$2001,"<"&EDATE($AB5,1),$E$2:$E$2001,AC$1) -> 33643.48 | AD5: =SUMIFS($I$2:$I$2001,$B$2:$B$2001,">="&$AB5,$B$2:$B$2001,"<"&EDATE($AB5,1),$E$2:$E$2001,AD$1) -> 46286.92 | AE5: =SUMIFS($I$2:$I$2001,$B$2:$B$2001,">="&$AB5,$B$2:$B$2001,"<"&EDATE($AB5,1),$E$2:$E$2001,AE$1) -> 96349.86 | AF5: =SUMIFS($I$2:$I$2001,$B$2:$B$2001,">="&$AB5,$B$2:$B$2001,"<"&EDATE($AB5,1),$E$2:$E$2001,AF$1) -> 23036.54 | AG5: =SUMIFS($I$2:$I$2001,$B$2:$B$2001,">="&$AB5,$B$2:$B$2001,"<"&EDATE($AB5,1),$E$2:$E$2001,AG$1) -> 46025.56 | AH5: =SUMIFS($I$2:$I$2001,$B$2:$B$2001,">="&$AB5,$B$2:$B$2001,"<"&EDATE($AB5,1),$E$2:$E$2001,AH$1) -> 170939.91 | AI5: =SUMIFS($I$2:$I$2001,$B$2:$B$2001,">="&$AB5,$B$2:$B$2001,"<"&EDATE($AB5,1),$E$2:$E$2001,AI$1) -> 48536.18 | AJ5: =SUMIFS($I$2:$I$2001,$B$2:$B$2001,">="&$AB5,$B$2:$B$2001,"<"&EDATE($AB5,1),$E$2:$E$2001,AJ$1) -> 12044.56 | ... BF5: =SUMIFS($I$2:$I$2001,$B$2:$B$2001,">="&$AB5,$B$2:$B$2001,"<"&EDATE($AB5,1),$E$2:$E$2001,BF$1) -> 36350.86 | BH5: =Products!A5 -> PROD-004 | BI5: =Products!B5 -> Laptop Bag | BJ5: =SUMIFS($I$2:$I$2001,$N$2:$N$2001,"West",$D$2:$D$2001,BH5) -> 198124.65 | BK5: =_xludf.RANK.EQ(BJ5,$BJ$2:$BJ$61,0) -> #NAME? | BL5: 0 | BM5: 0 | BN5: 0.023809524 | BO5: 0 | BP5: 1
A6: =Orders!A6 -> ORD-00005 | B6: =Orders!B6 -> 45611 | C6: =Orders!C6 -> CUST-0180 | D6: =Orders!D6 -> PROD-012 | E6: =Orders!E6 -> R008 | F6: =Orders!F6 -> 1 | G6: =Orders!G6 -> 3160 | H6: =Orders!H6 -> 26 | ... K6: =Orders!K6 -> Chennai | L6: =IFERROR(VLOOKUP(D6,Products!$A$2:$F$61,3,FALSE),"") -> Apparel | M6: =IFERROR(VLOOKUP(D6,Products!$A$2:$F$61,4,FALSE),"") -> 1886 | N6: =IFERROR(VLOOKUP(E6,Sales_Reps!$A$2:$E$31,3,FALSE),"") -> North | O6: =IFERROR(VLOOKUP(C6,Customers!$A$2:$F$301,5,FALSE),"") -> Retail | P6: =IFERROR(VLOOKUP(C6,Customers!$A$2:$F$301,3,FALSE),"") -> 36 | Q6: =IFERROR((G6-M6)/G6,0) -> 0.40316456 | R6: =IFERROR(VLOOKUP(C6,Customers!$A$2:$F$301,1,FALSE),"") -> CUST-0180 | S6: =IFERROR(VLOOKUP(D6,Products!$A$2:$F$61,6,FALSE),"") -> TRUE | T6: Q1.5 | U6: =VLOOKUP(INDEX($D$2:$D$2001,MATCH("ORD-01500",$A$2:$A$2001,0)),Products!$A$2:$F$61,3,FALSE) -> Electronics | V6: Chain lookup | W6: =Sales_Reps!A6 -> R005 | X6: =Sales_Reps!B6 -> Vikram Patel | Y6: =SUMIF($E$2:$E$2001,W6,$I$2:$I$2001) -> 782445.33 | Z6: =_xludf.RANK.EQ(Y6,$Y$2:$Y$31,0) -> #NAME? | AB6: =DATE(2024,5,1) -> 45413 | AC6: =SUMIFS($I$2:$I$2001,$B$2:$B$2001,">="&$AB6,$B$2:$B$2001,"<"&EDATE($AB6,1),$E$2:$E$2001,AC$1) -> 44809.66 | AD6: =SUMIFS($I$2:$I$2001,$B$2:$B$2001,">="&$AB6,$B$2:$B$2001,"<"&EDATE($AB6,1),$E$2:$E$2001,AD$1) -> 89794.86 | AE6: =SUMIFS($I$2:$I$2001,$B$2:$B$2001,">="&$AB6,$B$2:$B$2001,"<"&EDATE($AB6,1),$E$2:$E$2001,AE$1) -> 139257.72 | AF6: =SUMIFS($I$2:$I$2001,$B$2:$B$2001,">="&$AB6,$B$2:$B$2001,"<"&EDATE($AB6,1),$E$2:$E$2001,AF$1) -> 140739.8 | AG6: =SUMIFS($I$2:$I$2001,$B$2:$B$2001,">="&$AB6,$B$2:$B$2001,"<"&EDATE($AB6,1),$E$2:$E$2001,AG$1) -> 67702.82 | AH6: =SUMIFS($I$2:$I$2001,$B$2:$B$2001,">="&$AB6,$B$2:$B$2001,"<"&EDATE($AB6,1),$E$2:$E$2001,AH$1) -> 78322.48 | AI6: =SUMIFS($I$2:$I$2001,$B$2:$B$2001,">="&$AB6,$B$2:$B$2001,"<"&EDATE($AB6,1),$E$2:$E$2001,AI$1) -> 41157.84 | AJ6: =SUMIFS($I$2:$I$2001,$B$2:$B$2001,">="&$AB6,$B$2:$B$2001,"<"&EDATE($AB6,1),$E$2:$E$2001,AJ$1) -> 67200.57 | ... BF6: =SUMIFS($I$2:$I$2001,$B$2:$B$2001,">="&$AB6,$B$2:$B$2001,"<"&EDATE($AB6,1),$E$2:$E$2001,BF$1) -> 47579.17 | BH6: =Products!A6 -> PROD-005 | BI6: =Products!B6 -> Power Bank | BJ6: =SUMIFS($I$2:$I$2001,$N$2:$N$2001,"West",$D$2:$D$2001,BH6) -> 7449.9 | BK6: =_xludf.RANK.EQ(BJ6,$BJ$2:$BJ$61,0) -> #NAME? | BL6: 0 | BM6: 0 | BN6: 0.018867925 | BO6: 0 | BP6: 0
A7: =Orders!A7 -> ORD-00006 | B7: =Orders!B7 -> 45406 | C7: =Orders!C7 -> CUST-0275 | D7: =Orders!D7 -> PROD-032 | E7: =Orders!E7 -> R025 | F7: =Orders!F7 -> 4 | G7: =Orders!G7 -> 370 | H7: =Orders!H7 -> 29 | ... K7: =Orders!K7 -> Mumbai | L7: =IFERROR(VLOOKUP(D7,Products!$A$2:$F$61,3,FALSE),"") -> Home | M7: =IFERROR(VLOOKUP(D7,Products!$A$2:$F$61,4,FALSE),"") -> 288 | N7: =IFERROR(VLOOKUP(E7,Sales_Reps!$A$2:$E$31,3,FALSE),"") -> West | O7: =IFERROR(VLOOKUP(C7,Customers!$A$2:$F$301,5,FALSE),"") -> Retail | P7: =IFERROR(VLOOKUP(C7,Customers!$A$2:$F$301,3,FALSE),"") -> 36 | Q7: =IFERROR((G7-M7)/G7,0) -> 0.22162162 | R7: =IFERROR(VLOOKUP(C7,Customers!$A$2:$F$301,1,FALSE),"") -> CUST-0275 | S7: =IFERROR(VLOOKUP(D7,Products!$A$2:$F$61,6,FALSE),"") -> TRUE | T7: Q1.6 | U7: =VLOOKUP(INDEX($H$2:$H$2001,MATCH("ORD-00789",$A$2:$A$2001,0)),Q1_Lookups!$B$18:$C$21,2,TRUE) -> Bronze | V7: Approximate VLOOKUP | W7: =Sales_Reps!A7 -> R006 | X7: =Sales_Reps!B7 -> Neha Desai | Y7: =SUMIF($E$2:$E$2001,W7,$I$2:$I$2001) -> 1138648.7 | Z7: =_xludf.RANK.EQ(Y7,$Y$2:$Y$31,0) -> #NAME? | AB7: =DATE(2024,6,1) -> 45444 | AC7: =SUMIFS($I$2:$I$2001,$B$2:$B$2001,">="&$AB7,$B$2:$B$2001,"<"&EDATE($AB7,1),$E$2:$E$2001,AC$1) -> 82789.95 | AD7: =SUMIFS($I$2:$I$2001,$B$2:$B$2001,">="&$AB7,$B$2:$B$2001,"<"&EDATE($AB7,1),$E$2:$E$2001,AD$1) -> 82753.37 | AE7: =SUMIFS($I$2:$I$2001,$B$2:$B$2001,">="&$AB7,$B$2:$B$2001,"<"&EDATE($AB7,1),$E$2:$E$2001,AE$1) -> 37966.09 | AF7: =SUMIFS($I$2:$I$2001,$B$2:$B$2001,">="&$AB7,$B$2:$B$2001,"<"&EDATE($AB7,1),$E$2:$E$2001,AF$1) -> 42388.12 | AG7: =SUMIFS($I$2:$I$2001,$B$2:$B$2001,">="&$AB7,$B$2:$B$2001,"<"&EDATE($AB7,1),$E$2:$E$2001,AG$1) -> 113205.32 | AH7: =SUMIFS($I$2:$I$2001,$B$2:$B$2001,">="&$AB7,$B$2:$B$2001,"<"&EDATE($AB7,1),$E$2:$E$2001,AH$1) -> 191251.6 | AI7: =SUMIFS($I$2:$I$2001,$B$2:$B$2001,">="&$AB7,$B$2:$B$2001,"<"&EDATE($AB7,1),$E$2:$E$2001,AI$1) -> 58895.11 | AJ7: =SUMIFS($I$2:$I$2001,$B$2:$B$2001,">="&$AB7,$B$2:$B$2001,"<"&EDATE($AB7,1),$E$2:$E$2001,AJ$1) -> 82481.44 | ... BF7: =SUMIFS($I$2:$I$2001,$B$2:$B$2001,">="&$AB7,$B$2:$B$2001,"<"&EDATE($AB7,1),$E$2:$E$2001,BF$1) -> 67486.9 | BH7: =Products!A7 -> PROD-006 | BI7: =Products!B7 -> Bluetooth Speaker | BJ7: =SUMIFS($I$2:$I$2001,$N$2:$N$2001,"West",$D$2:$D$2001,BH7) -> 100869.76 | BK7: =_xludf.RANK.EQ(BJ7,$BJ$2:$BJ$61,0) -> #NAME? | BL7: 0 | BM7: 0 | BN7: 0.018867925 | BO7: 0 | BP7: 0
A8: =Orders!A8 -> ORD-00007 | B8: =Orders!B8 -> 45455 | C8: =Orders!C8 -> CUST-0293 | D8: =Orders!D8 -> PROD-057 | E8: =Orders!E8 -> R024 | F8: =Orders!F8 -> 3 | G8: =Orders!G8 -> 960 | H8: =Orders!H8 -> 5.8 | ... K8: =Orders!K8 -> Bengaluru | L8: =IFERROR(VLOOKUP(D8,Products!$A$2:$F$61,3,FALSE),"") -> Sports | M8: =IFERROR(VLOOKUP(D8,Products!$A$2:$F$61,4,FALSE),"") -> 705 | N8: =IFERROR(VLOOKUP(E8,Sales_Reps!$A$2:$E$31,3,FALSE),"") -> West | O8: =IFERROR(VLOOKUP(C8,Customers!$A$2:$F$301,5,FALSE),"") -> Retail | P8: =IFERROR(VLOOKUP(C8,Customers!$A$2:$F$301,3,FALSE),"") -> 27 | Q8: =IFERROR((G8-M8)/G8,0) -> 0.265625 | R8: =IFERROR(VLOOKUP(C8,Customers!$A$2:$F$301,1,FALSE),"") -> CUST-0293 | S8: =IFERROR(VLOOKUP(D8,Products!$A$2:$F$61,6,FALSE),"") -> TRUE | T8: Q1.7 | U8: =INDEX(Sales_Reps!$B$2:$B$31,MATCH(INDEX($E$2:$E$2001,MATCH("ORD-01234",$A$2:$A$2001,0)),Sales_Reps!$A$2:$A$31,0))&" ("&INDEX(Sales_Reps!$C$2:$C$31,MATCH(INDEX($E$2:$E$2001,MATCH("ORD-01234",$A$2:$A$2001,0)),Sales_Reps!$A$2:$A$31,0))&")" -> Sanjay Kapoor (South) | V8: Two lookups joined with & | W8: =Sales_Reps!A8 -> R007 | X8: =Sales_Reps!B8 -> Suresh Menon | Y8: =SUMIF($E$2:$E$2001,W8,$I$2:$I$2001) -> 855749.68 | Z8: =_xludf.RANK.EQ(Y8,$Y$2:$Y$31,0) -> #NAME? | AB8: =DATE(2024,7,1) -> 45474 | AC8: =SUMIFS($I$2:$I$2001,$B$2:$B$2001,">="&$AB8,$B$2:$B$2001,"<"&EDATE($AB8,1),$E$2:$E$2001,AC$1) -> 28761.2 | AD8: =SUMIFS($I$2:$I$2001,$B$2:$B$2001,">="&$AB8,$B$2:$B$2001,"<"&EDATE($AB8,1),$E$2:$E$2001,AD$1) -> 62949.74 | AE8: =SUMIFS($I$2:$I$2001,$B$2:$B$2001,">="&$AB8,$B$2:$B$2001,"<"&EDATE($AB8,1),$E$2:$E$2001,AE$1) -> 185921.75 | AF8: =SUMIFS($I$2:$I$2001,$B$2:$B$2001,">="&$AB8,$B$2:$B$2001,"<"&EDATE($AB8,1),$E$2:$E$2001,AF$1) -> 7823.48 | AG8: =SUMIFS($I$2:$I$2001,$B$2:$B$2001,">="&$AB8,$B$2:$B$2001,"<"&EDATE($AB8,1),$E$2:$E$2001,AG$1) -> 20649.35 | AH8: =SUMIFS($I$2:$I$2001,$B$2:$B$2001,">="&$AB8,$B$2:$B$2001,"<"&EDATE($AB8,1),$E$2:$E$2001,AH$1) -> 38479.32 | AI8: =SUMIFS($I$2:$I$2001,$B$2:$B$2001,">="&$AB8,$B$2:$B$2001,"<"&EDATE($AB8,1),$E$2:$E$2001,AI$1) -> 11528.24 | AJ8: =SUMIFS($I$2:$I$2001,$B$2:$B$2001,">="&$AB8,$B$2:$B$2001,"<"&EDATE($AB8,1),$E$2:$E$2001,AJ$1) -> 75853.47 | ... BF8: =SUMIFS($I$2:$I$2001,$B$2:$B$2001,">="&$AB8,$B$2:$B$2001,"<"&EDATE($AB8,1),$E$2:$E$2001,BF$1) -> 89271.18 | BH8: =Products!A8 -> PROD-007 | BI8: =Products!B8 -> USB-C Cable | BJ8: =SUMIFS($I$2:$I$2001,$N$2:$N$2001,"West",$D$2:$D$2001,BH8) -> 38531.35 | BK8: =_xludf.RANK.EQ(BJ8,$BJ$2:$BJ$61,0) -> #NAME? | BL8: 0 | BM8: 0 | BN8: 0.021276596 | BO8: 0 | BP8: 0
A9: =Orders!A9 -> ORD-00008 | B9: =Orders!B9 -> 45617 | C9: =Orders!C9 -> CUST-0281 | D9: =Orders!D9 -> PROD-007 | E9: =Orders!E9 -> R019 | F9: =Orders!F9 -> 8 | G9: =Orders!G9 -> 1430 | H9: =Orders!H9 -> 2.4 | ... K9: =Orders!K9 -> Bengaluru | L9: =IFERROR(VLOOKUP(D9,Products!$A$2:$F$61,3,FALSE),"") -> Electronics | M9: =IFERROR(VLOOKUP(D9,Products!$A$2:$F$61,4,FALSE),"") -> 861 | N9: =IFERROR(VLOOKUP(E9,Sales_Reps!$A$2:$E$31,3,FALSE),"") -> East | O9: =IFERROR(VLOOKUP(C9,Customers!$A$2:$F$301,5,FALSE),"") -> Corporate | P9: =IFERROR(VLOOKUP(C9,Customers!$A$2:$F$301,3,FALSE),"") -> 57 | Q9: =IFERROR((G9-M9)/G9,0) -> 0.3979021 | R9: =IFERROR(VLOOKUP(C9,Customers!$A$2:$F$301,1,FALSE),"") -> CUST-0281 | S9: =IFERROR(VLOOKUP(D9,Products!$A$2:$F$61,6,FALSE),"") -> TRUE | T9: Q1.8 | U9: =INDEX(Sales_Reps!$B$2:$B$31,MATCH(INDEX(Sales_Reps!$E$2:$E$31,MATCH("R017",Sales_Reps!$A$2:$A$31,0)),Sales_Reps!$A$2:$A$31,0)) -> Amit Singh | V9: Self lookup | W9: =Sales_Reps!A9 -> R008 | X9: =Sales_Reps!B9 -> Kavita Patel | Y9: =SUMIF($E$2:$E$2001,W9,$I$2:$I$2001) -> 861553.33 | Z9: =_xludf.RANK.EQ(Y9,$Y$2:$Y$31,0) -> #NAME? | AB9: =DATE(2024,8,1) -> 45505 | AC9: =SUMIFS($I$2:$I$2001,$B$2:$B$2001,">="&$AB9,$B$2:$B$2001,"<"&EDATE($AB9,1),$E$2:$E$2001,AC$1) -> 92676.92 | AD9: =SUMIFS($I$2:$I$2001,$B$2:$B$2001,">="&$AB9,$B$2:$B$2001,"<"&EDATE($AB9,1),$E$2:$E$2001,AD$1) -> 134500.5 | AE9: =SUMIFS($I$2:$I$2001,$B$2:$B$2001,">="&$AB9,$B$2:$B$2001,"<"&EDATE($AB9,1),$E$2:$E$2001,AE$1) -> 114656.27 | AF9: =SUMIFS($I$2:$I$2001,$B$2:$B$2001,">="&$AB9,$B$2:$B$2001,"<"&EDATE($AB9,1),$E$2:$E$2001,AF$1) -> 55975.34 | AG9: =SUMIFS($I$2:$I$2001,$B$2:$B$2001,">="&$AB9,$B$2:$B$2001,"<"&EDATE($AB9,1),$E$2:$E$2001,AG$1) -> 15060.28 | AH9: =SUMIFS($I$2:$I$2001,$B$2:$B$2001,">="&$AB9,$B$2:$B$2001,"<"&EDATE($AB9,1),$E$2:$E$2001,AH$1) -> 61857.9 | AI9: =SUMIFS($I$2:$I$2001,$B$2:$B$2001,">="&$AB9,$B$2:$B$2001,"<"&EDATE($AB9,1),$E$2:$E$2001,AI$1) -> 70196.8 | AJ9: =SUMIFS($I$2:$I$2001,$B$2:$B$2001,">="&$AB9,$B$2:$B$2001,"<"&EDATE($AB9,1),$E$2:$E$2001,AJ$1) -> 61043.44 | ... BF9: =SUMIFS($I$2:$I$2001,$B$2:$B$2001,">="&$AB9,$B$2:$B$2001,"<"&EDATE($AB9,1),$E$2:$E$2001,BF$1) -> 74000.9 | BH9: =Products!A9 -> PROD-008 | BI9: =Products!B9 -> Wireless Mouse | BJ9: =SUMIFS($I$2:$I$2001,$N$2:$N$2001,"West",$D$2:$D$2001,BH9) -> 7807.1 | BK9: =_xludf.RANK.EQ(BJ9,$BJ$2:$BJ$61,0) -> #NAME? | BL9: 0 | BM9: 0 | BN9: 0.018867925 | BO9: 0 | BP9: 0
A10: =Orders!A10 -> ORD-00009 | B10: =Orders!B10 -> 45549 | C10: =Orders!C10 -> CUST-0260 | D10: =Orders!D10 -> PROD-038 | E10: =Orders!E10 -> R008 | F10: =Orders!F10 -> 3 | G10: =Orders!G10 -> 5490 | H10: =Orders!H10 -> 14.2 | ... K10: =Orders!K10 -> Bengaluru | L10: =IFERROR(VLOOKUP(D10,Products!$A$2:$F$61,3,FALSE),"") -> Home | M10: =IFERROR(VLOOKUP(D10,Products!$A$2:$F$61,4,FALSE),"") -> 2549 | N10: =IFERROR(VLOOKUP(E10,Sales_Reps!$A$2:$E$31,3,FALSE),"") -> North | O10: =IFERROR(VLOOKUP(C10,Customers!$A$2:$F$301,5,FALSE),"") -> Retail | P10: =IFERROR(VLOOKUP(C10,Customers!$A$2:$F$301,3,FALSE),"") -> 42 | Q10: =IFERROR((G10-M10)/G10,0) -> 0.53570128 | R10: =IFERROR(VLOOKUP(C10,Customers!$A$2:$F$301,1,FALSE),"") -> CUST-0260 | S10: =IFERROR(VLOOKUP(D10,Products!$A$2:$F$61,6,FALSE),"") -> TRUE | T10: Q2.1 | U10: 20 | V10: Row-by-row duplicate check | W10: =Sales_Reps!A10 -> R009 | X10: =Sales_Reps!B10 -> Manoj Patel | Y10: =SUMIF($E$2:$E$2001,W10,$I$2:$I$2001) -> 914554.72 | Z10: =_xludf.RANK.EQ(Y10,$Y$2:$Y$31,0) -> #NAME? | AB10: =DATE(2024,9,1) -> 45536 | AC10: =SUMIFS($I$2:$I$2001,$B$2:$B$2001,">="&$AB10,$B$2:$B$2001,"<"&EDATE($AB10,1),$E$2:$E$2001,AC$1) -> 88884.34 | AD10: =SUMIFS($I$2:$I$2001,$B$2:$B$2001,">="&$AB10,$B$2:$B$2001,"<"&EDATE($AB10,1),$E$2:$E$2001,AD$1) -> 91647.29 | AE10: =SUMIFS($I$2:$I$2001,$B$2:$B$2001,">="&$AB10,$B$2:$B$2001,"<"&EDATE($AB10,1),$E$2:$E$2001,AE$1) -> 69896.72 | AF10: =SUMIFS($I$2:$I$2001,$B$2:$B$2001,">="&$AB10,$B$2:$B$2001,"<"&EDATE($AB10,1),$E$2:$E$2001,AF$1) -> 46944.28 | AG10: =SUMIFS($I$2:$I$2001,$B$2:$B$2001,">="&$AB10,$B$2:$B$2001,"<"&EDATE($AB10,1),$E$2:$E$2001,AG$1) -> 81963.69 | AH10: =SUMIFS($I$2:$I$2001,$B$2:$B$2001,">="&$AB10,$B$2:$B$2001,"<"&EDATE($AB10,1),$E$2:$E$2001,AH$1) -> 76627.83 | AI10: =SUMIFS($I$2:$I$2001,$B$2:$B$2001,">="&$AB10,$B$2:$B$2001,"<"&EDATE($AB10,1),$E$2:$E$2001,AI$1) -> 52194.15 | AJ10: =SUMIFS($I$2:$I$2001,$B$2:$B$2001,">="&$AB10,$B$2:$B$2001,"<"&EDATE($AB10,1),$E$2:$E$2001,AJ$1) -> 49404.64 | ... BF10: =SUMIFS($I$2:$I$2001,$B$2:$B$2001,">="&$AB10,$B$2:$B$2001,"<"&EDATE($AB10,1),$E$2:$E$2001,BF$1) -> 26448.21 | BH10: =Products!A10 -> PROD-009 | BI10: =Products!B10 -> Mechanical Keyboard | BJ10: =SUMIFS($I$2:$I$2001,$N$2:$N$2001,"West",$D$2:$D$2001,BH10) -> 64207.38 | BK10: =_xludf.RANK.EQ(BJ10,$BJ$2:$BJ$61,0) -> #NAME? | BL10: 0 | BM10: 0 | BN10: 0.018518519 | BO10: 0 | BP10: 0
A11: =Orders!A11 -> ORD-00010 | B11: =Orders!B11 -> 45396 | C11: =Orders!C11 -> CUST-0147 | D11: =Orders!D11 -> PROD-030 | E11: =Orders!E11 -> R028 | F11: =Orders!F11 -> 3 | G11: =Orders!G11 -> 970 | H11: =Orders!H11 -> 1.2 | ... K11: =Orders!K11 -> Pune | L11: =IFERROR(VLOOKUP(D11,Products!$A$2:$F$61,3,FALSE),"") -> Grocery | M11: =IFERROR(VLOOKUP(D11,Products!$A$2:$F$61,4,FALSE),"") -> 434 | N11: =IFERROR(VLOOKUP(E11,Sales_Reps!$A$2:$E$31,3,FALSE),"") -> West | O11: =IFERROR(VLOOKUP(C11,Customers!$A$2:$F$301,5,FALSE),"") -> Retail | P11: =IFERROR(VLOOKUP(C11,Customers!$A$2:$F$301,3,FALSE),"") -> 56 | Q11: =IFERROR((G11-M11)/G11,0) -> 0.55257732 | R11: =IFERROR(VLOOKUP(C11,Customers!$A$2:$F$301,1,FALSE),"") -> CUST-0147 | S11: =IFERROR(VLOOKUP(D11,Products!$A$2:$F$61,6,FALSE),"") -> TRUE | T11: Q2.2 | U11: 15 | V11: LEN vs TRIM helper | W11: =Sales_Reps!A11 -> R010 | X11: =Sales_Reps!B11 -> Divya Rao | Y11: =SUMIF($E$2:$E$2001,W11,$I$2:$I$2001) -> 880345.2 | Z11: =_xludf.RANK.EQ(Y11,$Y$2:$Y$31,0) -> #NAME? | AB11: =DATE(2024,10,1) -> 45566 | AC11: =SUMIFS($I$2:$I$2001,$B$2:$B$2001,">="&$AB11,$B$2:$B$2001,"<"&EDATE($AB11,1),$E$2:$E$2001,AC$1) -> 37753.9 | AD11: =SUMIFS($I$2:$I$2001,$B$2:$B$2001,">="&$AB11,$B$2:$B$2001,"<"&EDATE($AB11,1),$E$2:$E$2001,AD$1) -> 35751.81 | AE11: =SUMIFS($I$2:$I$2001,$B$2:$B$2001,">="&$AB11,$B$2:$B$2001,"<"&EDATE($AB11,1),$E$2:$E$2001,AE$1) -> 29309.98 | AF11: =SUMIFS($I$2:$I$2001,$B$2:$B$2001,">="&$AB11,$B$2:$B$2001,"<"&EDATE($AB11,1),$E$2:$E$2001,AF$1) -> 43456.18 | AG11: =SUMIFS($I$2:$I$2001,$B$2:$B$2001,">="&$AB11,$B$2:$B$2001,"<"&EDATE($AB11,1),$E$2:$E$2001,AG$1) -> 99252.77 | AH11: =SUMIFS($I$2:$I$2001,$B$2:$B$2001,">="&$AB11,$B$2:$B$2001,"<"&EDATE($AB11,1),$E$2:$E$2001,AH$1) -> 52942.27 | AI11: =SUMIFS($I$2:$I$2001,$B$2:$B$2001,">="&$AB11,$B$2:$B$2001,"<"&EDATE($AB11,1),$E$2:$E$2001,AI$1) -> 57313.75 | AJ11: =SUMIFS($I$2:$I$2001,$B$2:$B$2001,">="&$AB11,$B$2:$B$2001,"<"&EDATE($AB11,1),$E$2:$E$2001,AJ$1) -> 26620.46 | ... BF11: =SUMIFS($I$2:$I$2001,$B$2:$B$2001,">="&$AB11,$B$2:$B$2001,"<"&EDATE($AB11,1),$E$2:$E$2001,BF$1) -> 40669.76 | BH11: =Products!A11 -> PROD-010 | BI11: =Products!B11 -> Tablet Stand | BJ11: =SUMIFS($I$2:$I$2001,$N$2:$N$2001,"West",$D$2:$D$2001,BH11) -> 67393.92 | BK11: =_xludf.RANK.EQ(BJ11,$BJ$2:$BJ$61,0) -> #NAME? | BL11: 0 | BM11: 0 | BN11: 0.018518519 | BO11: 0 | BP11: 0
A12: =Orders!A12 -> ORD-00011 | B12: =Orders!B12 -> 45560 | C12: =Orders!C12 -> CUST-0204 | D12: =Orders!D12 -> PROD-024 | E12: =Orders!E12 -> R010 | F12: =Orders!F12 -> 7 | G12: =Orders!G12 -> 2270 | H12: =Orders!H12 -> 7.1 | ... K12: =Orders!K12 -> Hyderabad | L12: =IFERROR(VLOOKUP(D12,Products!$A$2:$F$61,3,FALSE),"") -> Grocery | M12: =IFERROR(VLOOKUP(D12,Products!$A$2:$F$61,4,FALSE),"") -> 1203 | N12: =IFERROR(VLOOKUP(E12,Sales_Reps!$A$2:$E$31,3,FALSE),"") -> South | O12: =IFERROR(VLOOKUP(C12,Customers!$A$2:$F$301,5,FALSE),"") -> Retail | P12: =IFERROR(VLOOKUP(C12,Customers!$A$2:$F$301,3,FALSE),"") -> 60 | Q12: =IFERROR((G12-M12)/G12,0) -> 0.47004405 | R12: =IFERROR(VLOOKUP(C12,Customers!$A$2:$F$301,1,FALSE),"") -> CUST-0204 | S12: =IFERROR(VLOOKUP(D12,Products!$A$2:$F$61,6,FALSE),"") -> TRUE | T12: Q2.3 | U12: 6 | V12: Case-insensitive city helper | W12: =Sales_Reps!A12 -> R011 | X12: =Sales_Reps!B12 -> Anil Verma | Y12: =SUMIF($E$2:$E$2001,W12,$I$2:$I$2001) -> 735207.76 | Z12: =_xludf.RANK.EQ(Y12,$Y$2:$Y$31,0) -> #NAME? | AB12: =DATE(2024,11,1) -> 45597 | AC12: =SUMIFS($I$2:$I$2001,$B$2:$B$2001,">="&$AB12,$B$2:$B$2001,"<"&EDATE($AB12,1),$E$2:$E$2001,AC$1) -> 72215.41 | AD12: =SUMIFS($I$2:$I$2001,$B$2:$B$2001,">="&$AB12,$B$2:$B$2001,"<"&EDATE($AB12,1),$E$2:$E$2001,AD$1) -> 158277.82 | AE12: =SUMIFS($I$2:$I$2001,$B$2:$B$2001,">="&$AB12,$B$2:$B$2001,"<"&EDATE($AB12,1),$E$2:$E$2001,AE$1) -> 106760.75 | AF12: =SUMIFS($I$2:$I$2001,$B$2:$B$2001,">="&$AB12,$B$2:$B$2001,"<"&EDATE($AB12,1),$E$2:$E$2001,AF$1) -> 38491.18 | AG12: =SUMIFS($I$2:$I$2001,$B$2:$B$2001,">="&$AB12,$B$2:$B$2001,"<"&EDATE($AB12,1),$E$2:$E$2001,AG$1) -> 55570.99 | AH12: =SUMIFS($I$2:$I$2001,$B$2:$B$2001,">="&$AB12,$B$2:$B$2001,"<"&EDATE($AB12,1),$E$2:$E$2001,AH$1) -> 81500.24 | AI12: =SUMIFS($I$2:$I$2001,$B$2:$B$2001,">="&$AB12,$B$2:$B$2001,"<"&EDATE($AB12,1),$E$2:$E$2001,AI$1) -> 130208.9 | AJ12: =SUMIFS($I$2:$I$2001,$B$2:$B$2001,">="&$AB12,$B$2:$B$2001,"<"&EDATE($AB12,1),$E$2:$E$2001,AJ$1) -> 64537.26 | ... BF12: =SUMIFS($I$2:$I$2001,$B$2:$B$2001,">="&$AB12,$B$2:$B$2001,"<"&EDATE($AB12,1),$E$2:$E$2001,BF$1) -> 119624.49 | BH12: =Products!A12 -> PROD-011 | BI12: =Products!B12 -> Cotton T-Shirt | BJ12: =SUMIFS($I$2:$I$2001,$N$2:$N$2001,"West",$D$2:$D$2001,BH12) -> 145224.3 | BK12: =_xludf.RANK.EQ(BJ12,$BJ$2:$BJ$61,0) -> #NAME? | BL12: 0 | BM12: 0 | BN12: 0.018867925 | BO12: 0 | BP12: 0
A13: =Orders!A13 -> ORD-00012 | B13: =Orders!B13 -> 45332 | C13: =Orders!C13 -> CUST-0147 | D13: =Orders!D13 -> PROD-010 | E13: =Orders!E13 -> R024 | F13: =Orders!F13 -> 9 | G13: =Orders!G13 -> 2640 | H13: =Orders!H13 -> 21.7 | ... K13: =Orders!K13 -> Pune | L13: =IFERROR(VLOOKUP(D13,Products!$A$2:$F$61,3,FALSE),"") -> Electronics | M13: =IFERROR(VLOOKUP(D13,Products!$A$2:$F$61,4,FALSE),"") -> 1149 | N13: =IFERROR(VLOOKUP(E13,Sales_Reps!$A$2:$E$31,3,FALSE),"") -> West | O13: =IFERROR(VLOOKUP(C13,Customers!$A$2:$F$301,5,FALSE),"") -> Retail | P13: =IFERROR(VLOOKUP(C13,Customers!$A$2:$F$301,3,FALSE),"") -> 56 | Q13: =IFERROR((G13-M13)/G13,0) -> 0.56477273 | R13: =IFERROR(VLOOKUP(C13,Customers!$A$2:$F$301,1,FALSE),"") -> CUST-0147 | S13: =IFERROR(VLOOKUP(D13,Products!$A$2:$F$61,6,FALSE),"") -> TRUE | T13: Q2.4 | U13: 30 | V13: Missing customer helper | W13: =Sales_Reps!A13 -> R012 | X13: =Sales_Reps!B13 -> Pooja Nair | Y13: =SUMIF($E$2:$E$2001,W13,$I$2:$I$2001) -> 901394.32 | Z13: =_xludf.RANK.EQ(Y13,$Y$2:$Y$31,0) -> #NAME? | AB13: =DATE(2024,12,1) -> 45627 | AC13: =SUMIFS($I$2:$I$2001,$B$2:$B$2001,">="&$AB13,$B$2:$B$2001,"<"&EDATE($AB13,1),$E$2:$E$2001,AC$1) -> 79450.52 | AD13: =SUMIFS($I$2:$I$2001,$B$2:$B$2001,">="&$AB13,$B$2:$B$2001,"<"&EDATE($AB13,1),$E$2:$E$2001,AD$1) -> 47673.25 | AE13: =SUMIFS($I$2:$I$2001,$B$2:$B$2001,">="&$AB13,$B$2:$B$2001,"<"&EDATE($AB13,1),$E$2:$E$2001,AE$1) -> 12325.54 | AF13: =SUMIFS($I$2:$I$2001,$B$2:$B$2001,">="&$AB13,$B$2:$B$2001,"<"&EDATE($AB13,1),$E$2:$E$2001,AF$1) -> 59066.32 | AG13: =SUMIFS($I$2:$I$2001,$B$2:$B$2001,">="&$AB13,$B$2:$B$2001,"<"&EDATE($AB13,1),$E$2:$E$2001,AG$1) -> 68580.8 | AH13: =SUMIFS($I$2:$I$2001,$B$2:$B$2001,">="&$AB13,$B$2:$B$2001,"<"&EDATE($AB13,1),$E$2:$E$2001,AH$1) -> 121741.5 | AI13: =SUMIFS($I$2:$I$2001,$B$2:$B$2001,">="&$AB13,$B$2:$B$2001,"<"&EDATE($AB13,1),$E$2:$E$2001,AI$1) -> 57922.93 | AJ13: =SUMIFS($I$2:$I$2001,$B$2:$B$2001,">="&$AB13,$B$2:$B$2001,"<"&EDATE($AB13,1),$E$2:$E$2001,AJ$1) -> 172732.12 | ... BF13: =SUMIFS($I$2:$I$2001,$B$2:$B$2001,">="&$AB13,$B$2:$B$2001,"<"&EDATE($AB13,1),$E$2:$E$2001,BF$1) -> 47706.74 | BH13: =Products!A13 -> PROD-012 | BI13: =Products!B13 -> Denim Jeans | BJ13: =SUMIFS($I$2:$I$2001,$N$2:$N$2001,"West",$D$2:$D$2001,BH13) -> 121770.6 | BK13: =_xludf.RANK.EQ(BJ13,$BJ$2:$BJ$61,0) -> #NAME? | BL13: 0 | BM13: 0 | BN13: 0.018867925 | BO13: 0 | BP13: 0
A14: =Orders!A14 -> ORD-00013 | B14: =Orders!B14 -> 45507 | C14: =Orders!C14 -> CUST-0280 | D14: =Orders!D14 -> PROD-002 | E14: =Orders!E14 -> R004 | F14: =Orders!F14 -> 3 | G14: =Orders!G14 -> 2600 | H14: =Orders!H14 -> 4.3 | ... K14: =Orders!K14 -> Delhi | L14: =IFERROR(VLOOKUP(D14,Products!$A$2:$F$61,3,FALSE),"") -> Electronics | M14: =IFERROR(VLOOKUP(D14,Products!$A$2:$F$61,4,FALSE),"") -> 1052 | N14: =IFERROR(VLOOKUP(E14,Sales_Reps!$A$2:$E$31,3,FALSE),"") -> North | O14: =IFERROR(VLOOKUP(C14,Customers!$A$2:$F$301,5,FALSE),"") -> SMB | P14: =IFERROR(VLOOKUP(C14,Customers!$A$2:$F$301,3,FALSE),"") -> 27 | Q14: =IFERROR((G14-M14)/G14,0) -> 0.59538462 | R14: =IFERROR(VLOOKUP(C14,Customers!$A$2:$F$301,1,FALSE),"") -> CUST-0280 | S14: =IFERROR(VLOOKUP(D14,Products!$A$2:$F$61,6,FALSE),"") -> TRUE | T14: Q2.5 | U14: 174 | V14: Inactive product helper | W14: =Sales_Reps!A14 -> R013 | X14: =Sales_Reps!B14 -> Sanjay Kapoor | Y14: =SUMIF($E$2:$E$2001,W14,$I$2:$I$2001) -> 811524.38 | Z14: =_xludf.RANK.EQ(Y14,$Y$2:$Y$31,0) -> #NAME? | BH14: =Products!A14 -> PROD-013 | BI14: =Products!B14 -> Formal Shirt | BJ14: =SUMIFS($I$2:$I$2001,$N$2:$N$2001,"West",$D$2:$D$2001,BH14) -> 85543.64 | BK14: =_xludf.RANK.EQ(BJ14,$BJ$2:$BJ$61,0) -> #NAME? | BL14: 0 | BM14: 0 | BN14: 0.023809524 | BO14: 0 | BP14: 0
A15: =Orders!A15 -> ORD-00014 | B15: =Orders!B15 -> 45466 | C15: =Orders!C15 -> CUST-0008 | D15: =Orders!D15 -> PROD-036 | E15: =Orders!E15 -> R025 | F15: =Orders!F15 -> 3 | G15: =Orders!G15 -> 3250 | H15: =Orders!H15 -> 14.1 | ... K15: =Orders!K15 -> Pune | L15: =IFERROR(VLOOKUP(D15,Products!$A$2:$F$61,3,FALSE),"") -> Home | M15: =IFERROR(VLOOKUP(D15,Products!$A$2:$F$61,4,FALSE),"") -> 1556 | N15: =IFERROR(VLOOKUP(E15,Sales_Reps!$A$2:$E$31,3,FALSE),"") -> West | O15: =IFERROR(VLOOKUP(C15,Customers!$A$2:$F$301,5,FALSE),"") -> SMB | P15: =IFERROR(VLOOKUP(C15,Customers!$A$2:$F$301,3,FALSE),"") -> 39 | Q15: =IFERROR((G15-M15)/G15,0) -> 0.52123077 | R15: =IFERROR(VLOOKUP(C15,Customers!$A$2:$F$301,1,FALSE),"") -> CUST-0008 | S15: =IFERROR(VLOOKUP(D15,Products!$A$2:$F$61,6,FALSE),"") -> TRUE | T15: Q2.6 | U15: =COUNTIFS($J$2:$J$2001,"Cancelled",$H$2:$H$2001,">20") -> 58 | V15: COUNTIFS | W15: =Sales_Reps!A15 -> R014 | X15: =Sales_Reps!B15 -> Ritu Menon | Y15: =SUMIF($E$2:$E$2001,W15,$I$2:$I$2001) -> 995713.54 | Z15: =_xludf.RANK.EQ(Y15,$Y$2:$Y$31,0) -> #NAME? | BH15: =Products!A15 -> PROD-014 | BI15: =Products!B15 -> Winter Jacket | BJ15: =SUMIFS($I$2:$I$2001,$N$2:$N$2001,"West",$D$2:$D$2001,BH15) -> 95390.62 | BK15: =_xludf.RANK.EQ(BJ15,$BJ$2:$BJ$61,0) -> #NAME? | BL15: 0 | BM15: 0 | BN15: 0.021276596 | BO15: 0 | BP15: 0
A16: =Orders!A16 -> ORD-00015 | B16: =Orders!B16 -> 45365 | C16: =Orders!C16 -> CUST-0052 | D16: =Orders!D16 -> PROD-060 | E16: =Orders!E16 -> R003 | F16: =Orders!F16 -> 1 | G16: =Orders!G16 -> 190 | H16: =Orders!H16 -> 20.7 | ... K16: =Orders!K16 -> Pune | L16: =IFERROR(VLOOKUP(D16,Products!$A$2:$F$61,3,FALSE),"") -> Sports | M16: =IFERROR(VLOOKUP(D16,Products!$A$2:$F$61,4,FALSE),"") -> 147 | N16: =IFERROR(VLOOKUP(E16,Sales_Reps!$A$2:$E$31,3,FALSE),"") -> North | O16: =IFERROR(VLOOKUP(C16,Customers!$A$2:$F$301,5,FALSE),"") -> Retail | P16: =IFERROR(VLOOKUP(C16,Customers!$A$2:$F$301,3,FALSE),"") -> 38 | Q16: =IFERROR((G16-M16)/G16,0) -> 0.22631579 | R16: =IFERROR(VLOOKUP(C16,Customers!$A$2:$F$301,1,FALSE),"") -> CUST-0052 | S16: =IFERROR(VLOOKUP(D16,Products!$A$2:$F$61,6,FALSE),"") -> TRUE | T16: Q3.1 | U16: =SUMIFS($I$2:$I$2001,$B$2:$B$2001,">="&DATE(2024,7,1),$B$2:$B$2001,"<="&DATE(2024,9,30),$K$2:$K$2001,"Mumbai") -> 1217239 | V16: SUMIFS: date range + city | W16: =Sales_Reps!A16 -> R015 | X16: =Sales_Reps!B16 -> Deepak Shah | Y16: =SUMIF($E$2:$E$2001,W16,$I$2:$I$2001) -> 1091740.2 | Z16: =_xludf.RANK.EQ(Y16,$Y$2:$Y$31,0) -> #NAME? | BH16: =Products!A16 -> PROD-015 | BI16: =Products!B16 -> Sports Shoes | BJ16: =SUMIFS($I$2:$I$2001,$N$2:$N$2001,"West",$D$2:$D$2001,BH16) -> 108190.72 | BK16: =_xludf.RANK.EQ(BJ16,$BJ$2:$BJ$61,0) -> #NAME? | BL16: 0 | BM16: 0 | BN16: 0.018867925 | BO16: 0 | BP16: 0
A17: =Orders!A17 -> ORD-00016 | B17: =Orders!B17 -> 45546 | C17: =Orders!C17 -> CUST-0184 | D17: =Orders!D17 -> PROD-058 | E17: =Orders!E17 -> R014 | F17: =Orders!F17 -> 7 | G17: =Orders!G17 -> 2400 | H17: =Orders!H17 -> 10.2 | ... K17: =Orders!K17 -> Pune | L17: =IFERROR(VLOOKUP(D17,Products!$A$2:$F$61,3,FALSE),"") -> Sports | M17: =IFERROR(VLOOKUP(D17,Products!$A$2:$F$61,4,FALSE),"") -> 974 | N17: =IFERROR(VLOOKUP(E17,Sales_Reps!$A$2:$E$31,3,FALSE),"") -> South | O17: =IFERROR(VLOOKUP(C17,Customers!$A$2:$F$301,5,FALSE),"") -> Retail | P17: =IFERROR(VLOOKUP(C17,Customers!$A$2:$F$301,3,FALSE),"") -> 63 | Q17: =IFERROR((G17-M17)/G17,0) -> 0.59416667 | R17: =IFERROR(VLOOKUP(C17,Customers!$A$2:$F$301,1,FALSE),"") -> CUST-0184 | S17: =IFERROR(VLOOKUP(D17,Products!$A$2:$F$61,6,FALSE),"") -> TRUE | T17: Q3.2 | U17: =COUNTIFS($H$2:$H$2001,">15",$J$2:$J$2001,"Completed") -> 723 | V17: COUNTIFS | W17: =Sales_Reps!A17 -> R016 | X17: =Sales_Reps!B17 -> Anjali Chopra | Y17: =SUMIF($E$2:$E$2001,W17,$I$2:$I$2001) -> 814563.71 | Z17: =_xludf.RANK.EQ(Y17,$Y$2:$Y$31,0) -> #NAME? | BH17: =Products!A17 -> PROD-016 | BI17: =Products!B17 -> Casual Sneakers | BJ17: =SUMIFS($I$2:$I$2001,$N$2:$N$2001,"West",$D$2:$D$2001,BH17) -> 12964.82 | BK17: =_xludf.RANK.EQ(BJ17,$BJ$2:$BJ$61,0) -> #NAME? | BL17: 0 | BM17: 0 | BN17: 0.023809524 | BO17: 0 | BP17: 0
A18: =Orders!A18 -> ORD-00017 | B18: =Orders!B18 -> 45512 | C18: =Orders!C18 -> CUST-0056 | D18: =Orders!D18 -> PROD-028 | E18: =Orders!E18 -> R023 | F18: =Orders!F18 -> 4 | G18: =Orders!G18 -> 3660 | H18: =Orders!H18 -> 2.6 | ... K18: =Orders!K18 -> Bengaluru | L18: =IFERROR(VLOOKUP(D18,Products!$A$2:$F$61,3,FALSE),"") -> Grocery | M18: =IFERROR(VLOOKUP(D18,Products!$A$2:$F$61,4,FALSE),"") -> 2214 | N18: =IFERROR(VLOOKUP(E18,Sales_Reps!$A$2:$E$31,3,FALSE),"") -> East | O18: =IFERROR(VLOOKUP(C18,Customers!$A$2:$F$301,5,FALSE),"") -> SMB | P18: =IFERROR(VLOOKUP(C18,Customers!$A$2:$F$301,3,FALSE),"") -> 46 | Q18: =IFERROR((G18-M18)/G18,0) -> 0.39508197 | R18: =IFERROR(VLOOKUP(C18,Customers!$A$2:$F$301,1,FALSE),"") -> CUST-0056 | S18: =IFERROR(VLOOKUP(D18,Products!$A$2:$F$61,6,FALSE),"") -> FALSE | T18: Q3.3 | U18: =AVERAGEIFS($I$2:$I$2001,$L$2:$L$2001,"Electronics",$O$2:$O$2001,"Corporate") -> 13981.402 | V18: AVERAGEIFS with helpers | W18: =Sales_Reps!A18 -> R017 | X18: =Sales_Reps!B18 -> Naveen Singh | Y18: =SUMIF($E$2:$E$2001,W18,$I$2:$I$2001) -> 780384.41 | Z18: =_xludf.RANK.EQ(Y18,$Y$2:$Y$31,0) -> #NAME? | BH18: =Products!A18 -> PROD-017 | BI18: =Products!B18 -> Silk Saree | BJ18: =SUMIFS($I$2:$I$2001,$N$2:$N$2001,"West",$D$2:$D$2001,BH18) -> 84699.95 | BK18: =_xludf.RANK.EQ(BJ18,$BJ$2:$BJ$61,0) -> #NAME? | BL18: 0 | BM18: 0 | BN18: 0.023809524 | BO18: 0 | BP18: 1
A19: =Orders!A19 -> ORD-00018 | B19: =Orders!B19 -> 45654 | C19: =Orders!C19 -> CUST-0273 | D19: =Orders!D19 -> PROD-047 | E19: =Orders!E19 -> R021 | F19: =Orders!F19 -> 8 | G19: =Orders!G19 -> 3450 | H19: =Orders!H19 -> 18.5 | ... K19: =Orders!K19 -> Hyderabad | L19: =IFERROR(VLOOKUP(D19,Products!$A$2:$F$61,3,FALSE),"") -> Beauty | M19: =IFERROR(VLOOKUP(D19,Products!$A$2:$F$61,4,FALSE),"") -> 2420 | N19: =IFERROR(VLOOKUP(E19,Sales_Reps!$A$2:$E$31,3,FALSE),"") -> East | O19: =IFERROR(VLOOKUP(C19,Customers!$A$2:$F$301,5,FALSE),"") -> Corporate | P19: =IFERROR(VLOOKUP(C19,Customers!$A$2:$F$301,3,FALSE),"") -> 32 | Q19: =IFERROR((G19-M19)/G19,0) -> 0.29855072 | R19: =IFERROR(VLOOKUP(C19,Customers!$A$2:$F$301,1,FALSE),"") -> CUST-0273 | S19: =IFERROR(VLOOKUP(D19,Products!$A$2:$F$61,6,FALSE),"") -> TRUE | T19: Q3.4 | U19: =SUM(LARGE($Y$2:$Y$31,1),LARGE($Y$2:$Y$31,2),LARGE($Y$2:$Y$31,3)) -> 3342678.5 | V19: Top 3 using LARGE | W19: =Sales_Reps!A19 -> R018 | X19: =Sales_Reps!B19 -> Shalini Patel | Y19: =SUMIF($E$2:$E$2001,W19,$I$2:$I$2001) -> 1112289.6 | Z19: =_xludf.RANK.EQ(Y19,$Y$2:$Y$31,0) -> #NAME? | BH19: =Products!A19 -> PROD-018 | BI19: =Products!B19 -> Kurta Set | BJ19: =SUMIFS($I$2:$I$2001,$N$2:$N$2001,"West",$D$2:$D$2001,BH19) -> 100288.76 | BK19: =_xludf.RANK.EQ(BJ19,$BJ$2:$BJ$61,0) -> #NAME? | BL19: 0 | BM19: 0 | BN19: 0.018867925 | BO19: 0 | BP19: 0
A20: =Orders!A20 -> ORD-00019 | B20: =Orders!B20 -> 45626 | C20: =Orders!C20 -> CUST-0182 | D20: =Orders!D20 -> PROD-051 | E20: =Orders!E20 -> R023 | F20: =Orders!F20 -> 5 | G20: =Orders!G20 -> 3450 | H20: =Orders!H20 -> 7.3 | ... K20: =Orders!K20 -> Mumbai | L20: =IFERROR(VLOOKUP(D20,Products!$A$2:$F$61,3,FALSE),"") -> Sports | M20: =IFERROR(VLOOKUP(D20,Products!$A$2:$F$61,4,FALSE),"") -> 2467 | N20: =IFERROR(VLOOKUP(E20,Sales_Reps!$A$2:$E$31,3,FALSE),"") -> East | O20: =IFERROR(VLOOKUP(C20,Customers!$A$2:$F$301,5,FALSE),"") -> Retail | P20: =IFERROR(VLOOKUP(C20,Customers!$A$2:$F$301,3,FALSE),"") -> 54 | Q20: =IFERROR((G20-M20)/G20,0) -> 0.28492754 | R20: =IFERROR(VLOOKUP(C20,Customers!$A$2:$F$301,1,FALSE),"") -> CUST-0182 | S20: =IFERROR(VLOOKUP(D20,Products!$A$2:$F$61,6,FALSE),"") -> TRUE | T20: Q3.5 | U20: =IF(SUMIFS($I$2:$I$2001,$E$2:$E$2001,"R015",$B$2:$B$2001,">="&DATE(2024,11,1),$B$2:$B$2001,"<="&DATE(2024,11,30))/INDEX(Targets!$A$2:$M$31,MATCH("R015",Targets!$A$2:$A$31,0),MATCH("Nov-24",Targets!$A$1:$M$1,0))<0.8,"Below",IF(SUMIFS($I$2:$I$2001,$E$2:$E$2001,"R015",$B$2:$B$2001,">="&DATE(2024,11,1),$B$2:$B$2001,"<="&DATE(2024,11,30))/INDEX(Targets!$A$2:$M$31,MATCH("R015",Targets!$A$2:$A$31,0),MATCH("Nov-24",Targets!$A$1:$M$1,0))<=1.2,"On Track","Exceeds")) -> Below | V20: Nested IF on actual / target | W20: =Sales_Reps!A20 -> R019 | X20: =Sales_Reps!B20 -> Prakash Shah | Y20: =SUMIF($E$2:$E$2001,W20,$I$2:$I$2001) -> 971183.52 | Z20: =_xludf.RANK.EQ(Y20,$Y$2:$Y$31,0) -> #NAME? | BH20: =Products!A20 -> PROD-019 | BI20: =Products!B20 -> Track Pants | BJ20: =SUMIFS($I$2:$I$2001,$N$2:$N$2001,"West",$D$2:$D$2001,BH20) -> 104993.28 | BK20: =_xludf.RANK.EQ(BJ20,$BJ$2:$BJ$61,0) -> #NAME? | BL20: 0 | BM20: 0 | BN20: 0.018867925 | BO20: 0 | BP20: 0
A21: =Orders!A21 -> ORD-00020 | B21: =Orders!B21 -> 45394 | C21: =Orders!C21 -> CUST-0265 | D21: =Orders!D21 -> PROD-040 | E21: =Orders!E21 -> R023 | F21: =Orders!F21 -> 8 | G21: =Orders!G21 -> 1080 | H21: =Orders!H21 -> 2.2 | ... K21: =Orders!K21 -> Chennai | L21: =IFERROR(VLOOKUP(D21,Products!$A$2:$F$61,3,FALSE),"") -> Home | M21: =IFERROR(VLOOKUP(D21,Products!$A$2:$F$61,4,FALSE),"") -> 519 | N21: =IFERROR(VLOOKUP(E21,Sales_Reps!$A$2:$E$31,3,FALSE),"") -> East | O21: =IFERROR(VLOOKUP(C21,Customers!$A$2:$F$301,5,FALSE),"") -> Retail | P21: =IFERROR(VLOOKUP(C21,Customers!$A$2:$F$301,3,FALSE),"") -> 49 | Q21: =IFERROR((G21-M21)/G21,0) -> 0.51944444 | R21: =IFERROR(VLOOKUP(C21,Customers!$A$2:$F$301,1,FALSE),"") -> CUST-0265 | S21: =IFERROR(VLOOKUP(D21,Products!$A$2:$F$61,6,FALSE),"") -> TRUE | T21: Q3.6 | U21: =SUMIFS($I$2:$I$2001,$O$2:$O$2001,"Corporate",$P$2:$P$2001,">=30",$P$2:$P$2001,"<=40") -> 982568.4 | V21: SUMIFS with age band | W21: =Sales_Reps!A21 -> R020 | X21: =Sales_Reps!B21 -> Meera Iyer | Y21: =SUMIF($E$2:$E$2001,W21,$I$2:$I$2001) -> 906107.71 | Z21: =_xludf.RANK.EQ(Y21,$Y$2:$Y$31,0) -> #NAME? | BH21: =Products!A21 -> PROD-020 | BI21: =Products!B21 -> Woolen Sweater | BJ21: =SUMIFS($I$2:$I$2001,$N$2:$N$2001,"West",$D$2:$D$2001,BH21) -> 9173.34 | BK21: =_xludf.RANK.EQ(BJ21,$BJ$2:$BJ$61,0) -> #NAME? | BL21: 0 | BM21: 0 | BN21: 0.019607843 | BO21: 0 | BP21: 0
A22: =Orders!A22 -> ORD-00021 | B22: =Orders!B22 -> 45470 | C22: =Orders!C22 -> CUST-0159 | D22: =Orders!D22 -> PROD-019 | E22: =Orders!E22 -> R006 | F22: =Orders!F22 -> 7 | G22: =Orders!G22 -> 2480 | H22: =Orders!H22 -> 28.7 | ... K22: =Orders!K22 -> Hyderabad | L22: =IFERROR(VLOOKUP(D22,Products!$A$2:$F$61,3,FALSE),"") -> Apparel | M22: =IFERROR(VLOOKUP(D22,Products!$A$2:$F$61,4,FALSE),"") -> 1173 | N22: =IFERROR(VLOOKUP(E22,Sales_Reps!$A$2:$E$31,3,FALSE),"") -> North | O22: =IFERROR(VLOOKUP(C22,Customers!$A$2:$F$301,5,FALSE),"") -> Retail | P22: =IFERROR(VLOOKUP(C22,Customers!$A$2:$F$301,3,FALSE),"") -> 32 | Q22: =IFERROR((G22-M22)/G22,0) -> 0.52701613 | R22: =IFERROR(VLOOKUP(C22,Customers!$A$2:$F$301,1,FALSE),"") -> CUST-0159 | S22: =IFERROR(VLOOKUP(D22,Products!$A$2:$F$61,6,FALSE),"") -> TRUE | T22: Q4.1 | U22: =SUMIFS($I$2:$I$2001,$N$2:$N$2001,"South",$L$2:$L$2001,"Electronics") -> 1314107.4 | V22: 2D pivot intersection | W22: =Sales_Reps!A22 -> R021 | X22: =Sales_Reps!B22 -> Gaurav Desai | Y22: =SUMIF($E$2:$E$2001,W22,$I$2:$I$2001) -> 761507.17 | Z22: =_xludf.RANK.EQ(Y22,$Y$2:$Y$31,0) -> #NAME? | BH22: =Products!A22 -> PROD-021 | BI22: =Products!B22 -> Basmati Rice 5kg | BJ22: =SUMIFS($I$2:$I$2001,$N$2:$N$2001,"West",$D$2:$D$2001,BH22) -> 90555.6 | BK22: =_xludf.RANK.EQ(BJ22,$BJ$2:$BJ$61,0) -> #NAME? | BL22: 0 | BM22: 0 | BN22: 0.018867925 | BO22: 0 | BP22: 0
A23: =Orders!A23 -> ORD-00022 | B23: =Orders!B23 -> 45354 | C23: =Orders!C23 -> CUST-0259 | D23: =Orders!D23 -> PROD-036 | E23: =Orders!E23 -> R030 | F23: =Orders!F23 -> 4 | G23: =Orders!G23 -> 3250 | H23: =Orders!H23 -> 24.6 | ... K23: =Orders!K23 -> Mumbai | L23: =IFERROR(VLOOKUP(D23,Products!$A$2:$F$61,3,FALSE),"") -> Home | M23: =IFERROR(VLOOKUP(D23,Products!$A$2:$F$61,4,FALSE),"") -> 1556 | N23: =IFERROR(VLOOKUP(E23,Sales_Reps!$A$2:$E$31,3,FALSE),"") -> West | O23: =IFERROR(VLOOKUP(C23,Customers!$A$2:$F$301,5,FALSE),"") -> Retail | P23: =IFERROR(VLOOKUP(C23,Customers!$A$2:$F$301,3,FALSE),"") -> 34 | Q23: =IFERROR((G23-M23)/G23,0) -> 0.52123077 | R23: =IFERROR(VLOOKUP(C23,Customers!$A$2:$F$301,1,FALSE),"") -> CUST-0259 | S23: =IFERROR(VLOOKUP(D23,Products!$A$2:$F$61,6,FALSE),"") -> TRUE | T23: Q4.2 | U23: =MAX($AC$2:$BF$13) -> 216421.52 | V23: MAX of month x rep table | W23: =Sales_Reps!A23 -> R022 | X23: =Sales_Reps!B23 -> Nisha Menon | Y23: =SUMIF($E$2:$E$2001,W23,$I$2:$I$2001) -> 1069570.5 | Z23: =_xludf.RANK.EQ(Y23,$Y$2:$Y$31,0) -> #NAME? | BH23: =Products!A23 -> PROD-022 | BI23: =Products!B23 -> Wheat Flour 10kg | BJ23: =SUMIFS($I$2:$I$2001,$N$2:$N$2001,"West",$D$2:$D$2001,BH23) -> 66299.89 | BK23: =_xludf.RANK.EQ(BJ23,$BJ$2:$BJ$61,0) -> #NAME? | BL23: 0 | BM23: 0 | BN23: 0.021276596 | BO23: 0 | BP23: 0
A24: =Orders!A24 -> ORD-00023 | B24: =Orders!B24 -> 45530 | C24: =Orders!C24 -> CUST-0107 | D24: =Orders!D24 -> PROD-015 | E24: =Orders!E24 -> R030 | F24: =Orders!F24 -> 9 | G24: =Orders!G24 -> 2720 | H24: =Orders!H24 -> 26.2 | ... K24: =Orders!K24 -> Pune | L24: =IFERROR(VLOOKUP(D24,Products!$A$2:$F$61,3,FALSE),"") -> Apparel | M24: =IFERROR(VLOOKUP(D24,Products!$A$2:$F$61,4,FALSE),"") -> 1962 | N24: =IFERROR(VLOOKUP(E24,Sales_Reps!$A$2:$E$31,3,FALSE),"") -> West | O24: =IFERROR(VLOOKUP(C24,Customers!$A$2:$F$301,5,FALSE),"") -> Retail | P24: =IFERROR(VLOOKUP(C24,Customers!$A$2:$F$301,3,FALSE),"") -> 50 | Q24: =IFERROR((G24-M24)/G24,0) -> 0.27867647 | R24: =IFERROR(VLOOKUP(C24,Customers!$A$2:$F$301,1,FALSE),"") -> CUST-0107 | S24: =IFERROR(VLOOKUP(D24,Products!$A$2:$F$61,6,FALSE),"") -> TRUE | T24: Q4.3 | U24: =SUMIFS($I$2:$I$2001,$N$2:$N$2001,"North",$L$2:$L$2001,"Apparel")/SUMIF($N$2:$N$2001,"North",$I$2:$I$2001) -> 0.1402315 | V24: % of North row total | W24: =Sales_Reps!A24 -> R023 | X24: =Sales_Reps!B24 -> Vinod Kumar | Y24: =SUMIF($E$2:$E$2001,W24,$I$2:$I$2001) -> 983787.48 | Z24: =_xludf.RANK.EQ(Y24,$Y$2:$Y$31,0) -> #NAME? | BH24: =Products!A24 -> PROD-023 | BI24: =Products!B24 -> Cooking Oil 5L | BJ24: =SUMIFS($I$2:$I$2001,$N$2:$N$2001,"West",$D$2:$D$2001,BH24) -> 84480.48 | BK24: =_xludf.RANK.EQ(BJ24,$BJ$2:$BJ$61,0) -> #NAME? | BL24: 0 | BM24: 0 | BN24: 0.018867925 | BO24: 0 | BP24: 0
A25: =Orders!A25 -> ORD-00024 | B25: =Orders!B25 -> 45472 | C25: =Orders!C25 -> CUST-0101 | D25: =Orders!D25 -> PROD-044 | E25: =Orders!E25 -> R003 | F25: =Orders!F25 -> 2 | G25: =Orders!G25 -> 1650 | H25: =Orders!H25 -> 9.4 | ... K25: =Orders!K25 -> Hyderabad | L25: =IFERROR(VLOOKUP(D25,Products!$A$2:$F$61,3,FALSE),"") -> Beauty | M25: =IFERROR(VLOOKUP(D25,Products!$A$2:$F$61,4,FALSE),"") -> 1222 | N25: =IFERROR(VLOOKUP(E25,Sales_Reps!$A$2:$E$31,3,FALSE),"") -> North | O25: =IFERROR(VLOOKUP(C25,Customers!$A$2:$F$301,5,FALSE),"") -> SMB | P25: =IFERROR(VLOOKUP(C25,Customers!$A$2:$F$301,3,FALSE),"") -> 40 | Q25: =IFERROR((G25-M25)/G25,0) -> 0.25939394 | R25: =IFERROR(VLOOKUP(C25,Customers!$A$2:$F$301,1,FALSE),"") -> CUST-0101 | S25: =IFERROR(VLOOKUP(D25,Products!$A$2:$F$61,6,FALSE),"") -> TRUE | T25: Q4.4 | U25: =SUMIFS($I$2:$I$2001,$B$2:$B$2001,">="&DATE(2024,10,1),$B$2:$B$2001,"<="&DATE(2024,12,31)) -> 6459443 | V25: SUMIFS for Q4 | W25: =Sales_Reps!A25 -> R024 | X25: =Sales_Reps!B25 -> Rekha Chopra | Y25: =SUMIF($E$2:$E$2001,W25,$I$2:$I$2001) -> 819558.58 | Z25: =_xludf.RANK.EQ(Y25,$Y$2:$Y$31,0) -> #NAME? | BH25: =Products!A25 -> PROD-024 | BI25: =Products!B25 -> Turmeric Powder 500g | BJ25: =SUMIFS($I$2:$I$2001,$N$2:$N$2001,"West",$D$2:$D$2001,BH25) -> 77055.15 | BK25: =_xludf.RANK.EQ(BJ25,$BJ$2:$BJ$61,0) -> #NAME? | BL25: 0 | BM25: 0 | BN25: 0.018867925 | BO25: 0 | BP25: 0
A26: =Orders!A26 -> ORD-00025 | B26: =Orders!B26 -> 45394 | C26: =Orders!C26 -> CUST-0142 | D26: =Orders!D26 -> PROD-043 | E26: =Orders!E26 -> R023 | F26: =Orders!F26 -> 6 | G26: =Orders!G26 -> 3350 | H26: =Orders!H26 -> 6.1 | ... K26: =Orders!K26 -> Chennai | L26: =IFERROR(VLOOKUP(D26,Products!$A$2:$F$61,3,FALSE),"") -> Beauty | M26: =IFERROR(VLOOKUP(D26,Products!$A$2:$F$61,4,FALSE),"") -> 1728 | N26: =IFERROR(VLOOKUP(E26,Sales_Reps!$A$2:$E$31,3,FALSE),"") -> East | O26: =IFERROR(VLOOKUP(C26,Customers!$A$2:$F$301,5,FALSE),"") -> Corporate | P26: =IFERROR(VLOOKUP(C26,Customers!$A$2:$F$301,3,FALSE),"") -> 55 | Q26: =IFERROR((G26-M26)/G26,0) -> 0.4841791 | R26: =IFERROR(VLOOKUP(C26,Customers!$A$2:$F$301,1,FALSE),"") -> CUST-0142 | S26: =IFERROR(VLOOKUP(D26,Products!$A$2:$F$61,6,FALSE),"") -> TRUE | T26: Q4.5 | U26: =AVERAGEIF($K$2:$K$2001,"Delhi",$Q$2:$Q$2001) -> 0.44880873 | V26: Average profit margin | W26: =Sales_Reps!A26 -> R025 | X26: =Sales_Reps!B26 -> Ashok Reddy | Y26: =SUMIF($E$2:$E$2001,W26,$I$2:$I$2001) -> 901298.89 | Z26: =_xludf.RANK.EQ(Y26,$Y$2:$Y$31,0) -> #NAME? | BH26: =Products!A26 -> PROD-025 | BI26: =Products!B26 -> Chili Powder 500g | BJ26: =SUMIFS($I$2:$I$2001,$N$2:$N$2001,"West",$D$2:$D$2001,BH26) -> 190994.58 | BK26: =_xludf.RANK.EQ(BJ26,$BJ$2:$BJ$61,0) -> #NAME? | BL26: 0 | BM26: 0 | BN26: 0.021276596 | BO26: 0 | BP26: 0
A27: =Orders!A27 -> ORD-00026 | B27: =Orders!B27 -> 45570 | C27: =Orders!C27 -> CUST-0250 | D27: =Orders!D27 -> PROD-054 | E27: =Orders!E27 -> R019 | F27: =Orders!F27 -> 2 | G27: =Orders!G27 -> 1010 | H27: =Orders!H27 -> 16.5 | ... K27: =Orders!K27 -> Delhi | L27: =IFERROR(VLOOKUP(D27,Products!$A$2:$F$61,3,FALSE),"") -> Sports | M27: =IFERROR(VLOOKUP(D27,Products!$A$2:$F$61,4,FALSE),"") -> 516 | N27: =IFERROR(VLOOKUP(E27,Sales_Reps!$A$2:$E$31,3,FALSE),"") -> East | O27: =IFERROR(VLOOKUP(C27,Customers!$A$2:$F$301,5,FALSE),"") -> Retail | P27: =IFERROR(VLOOKUP(C27,Customers!$A$2:$F$301,3,FALSE),"") -> 31 | Q27: =IFERROR((G27-M27)/G27,0) -> 0.48910891 | R27: =IFERROR(VLOOKUP(C27,Customers!$A$2:$F$301,1,FALSE),"") -> CUST-0250 | S27: =IFERROR(VLOOKUP(D27,Products!$A$2:$F$61,6,FALSE),"") -> TRUE | T27: Q5.1 | U27: =INDEX($X$2:$X$31,MATCH(7,$Z$2:$Z$31,0)) -> #N/A | V27: Rank and INDEX/MATCH | W27: =Sales_Reps!A27 -> R026 | X27: =Sales_Reps!B27 -> Sonia Malhotra | Y27: =SUMIF($E$2:$E$2001,W27,$I$2:$I$2001) -> 576305.08 | Z27: =_xludf.RANK.EQ(Y27,$Y$2:$Y$31,0) -> #NAME? | BH27: =Products!A27 -> PROD-026 | BI27: =Products!B27 -> Sugar 5kg | BJ27: =SUMIFS($I$2:$I$2001,$N$2:$N$2001,"West",$D$2:$D$2001,BH27) -> 179739.34 | BK27: =_xludf.RANK.EQ(BJ27,$BJ$2:$BJ$61,0) -> #NAME? | BL27: 0 | BM27: 0 | BN27: 0.018867925 | BO27: 0 | BP27: 0
A28: =Orders!A28 -> ORD-00027 | B28: =Orders!B28 -> 45401 | C28: =Orders!C28 -> CUST-0098 | D28: =Orders!D28 -> PROD-046 | E28: =Orders!E28 -> R006 | F28: =Orders!F28 -> 5 | G28: =Orders!G28 -> 4880 | H28: =Orders!H28 -> 23.6 | ... K28: =Orders!K28 -> Delhi | L28: =IFERROR(VLOOKUP(D28,Products!$A$2:$F$61,3,FALSE),"") -> Beauty | M28: =IFERROR(VLOOKUP(D28,Products!$A$2:$F$61,4,FALSE),"") -> 2768 | N28: =IFERROR(VLOOKUP(E28,Sales_Reps!$A$2:$E$31,3,FALSE),"") -> North | O28: =IFERROR(VLOOKUP(C28,Customers!$A$2:$F$301,5,FALSE),"") -> Retail | P28: =IFERROR(VLOOKUP(C28,Customers!$A$2:$F$301,3,FALSE),"") -> 52 | Q28: =IFERROR((G28-M28)/G28,0) -> 0.43278689 | R28: =IFERROR(VLOOKUP(C28,Customers!$A$2:$F$301,1,FALSE),"") -> CUST-0098 | S28: =IFERROR(VLOOKUP(D28,Products!$A$2:$F$61,6,FALSE),"") -> TRUE | T28: Q5.2 | U28: =SUMIFS($I$2:$I$2001,$B$2:$B$2001,"<="&DATE(2024,8,31)) -> 18050690 | V28: Running cumulative SUMIFS | W28: =Sales_Reps!A28 -> R027 | X28: =Sales_Reps!B28 -> Ramesh Bhatt | Y28: =SUMIF($E$2:$E$2001,W28,$I$2:$I$2001) -> 917092.62 | Z28: =_xludf.RANK.EQ(Y28,$Y$2:$Y$31,0) -> #NAME? | BH28: =Products!A28 -> PROD-027 | BI28: =Products!B28 -> Tea Leaves 1kg | BJ28: =SUMIFS($I$2:$I$2001,$N$2:$N$2001,"West",$D$2:$D$2001,BH28) -> 39599.28 | BK28: =_xludf.RANK.EQ(BJ28,$BJ$2:$BJ$61,0) -> #NAME? | BL28: 0 | BM28: 1 | BN28: 0.019607843 | BO28: 0 | BP28: 0
A29: =Orders!A29 -> ORD-00028 | B29: =Orders!B29 -> 45517 | C29: =Orders!C29 -> CUST-0143 | D29: =Orders!D29 -> PROD-003 | E29: =Orders!E29 -> R015 | F29: =Orders!F29 -> 7 | G29: =Orders!G29 -> 3570 | H29: =Orders!H29 -> 5.8 | ... K29: =Orders!K29 -> Chennai | L29: =IFERROR(VLOOKUP(D29,Products!$A$2:$F$61,3,FALSE),"") -> Electronics | M29: =IFERROR(VLOOKUP(D29,Products!$A$2:$F$61,4,FALSE),"") -> 1665 | N29: =IFERROR(VLOOKUP(E29,Sales_Reps!$A$2:$E$31,3,FALSE),"") -> South | O29: =IFERROR(VLOOKUP(C29,Customers!$A$2:$F$301,5,FALSE),"") -> SMB | P29: =IFERROR(VLOOKUP(C29,Customers!$A$2:$F$301,3,FALSE),"") -> 52 | Q29: =IFERROR((G29-M29)/G29,0) -> 0.53361345 | R29: =IFERROR(VLOOKUP(C29,Customers!$A$2:$F$301,1,FALSE),"") -> CUST-0143 | S29: =IFERROR(VLOOKUP(D29,Products!$A$2:$F$61,6,FALSE),"") -> TRUE | T29: Q5.3 | U29: =INDEX($BI$2:$BI$61,MATCH(2,$BK$2:$BK$61,0)) -> #N/A | V29: West product rank | W29: =Sales_Reps!A29 -> R028 | X29: =Sales_Reps!B29 -> Preeti Shah | Y29: =SUMIF($E$2:$E$2001,W29,$I$2:$I$2001) -> 880468.05 | Z29: =_xludf.RANK.EQ(Y29,$Y$2:$Y$31,0) -> #NAME? | BH29: =Products!A29 -> PROD-028 | BI29: =Products!B29 -> Coffee Beans 500g | BJ29: =SUMIFS($I$2:$I$2001,$N$2:$N$2001,"West",$D$2:$D$2001,BH29) -> 112574.28 | BK29: =_xludf.RANK.EQ(BJ29,$BJ$2:$BJ$61,0) -> #NAME? | BL29: 0 | BM29: 0 | BN29: 0.021276596 | BO29: 0 | BP29: 0
A30: =Orders!A30 -> ORD-00029 | B30: =Orders!B30 -> 45363 | C30: =Orders!C30 -> CUST-0086 | D30: =Orders!D30 -> PROD-048 | E30: =Orders!E30 -> R020 | F30: =Orders!F30 -> 9 | G30: =Orders!G30 -> 5100 | H30: =Orders!H30 -> 16.7 | ... K30: =Orders!K30 -> Hyderabad | L30: =IFERROR(VLOOKUP(D30,Products!$A$2:$F$61,3,FALSE),"") -> Beauty | M30: =IFERROR(VLOOKUP(D30,Products!$A$2:$F$61,4,FALSE),"") -> 2237 | N30: =IFERROR(VLOOKUP(E30,Sales_Reps!$A$2:$E$31,3,FALSE),"") -> East | O30: =IFERROR(VLOOKUP(C30,Customers!$A$2:$F$301,5,FALSE),"") -> Corporate | P30: =IFERROR(VLOOKUP(C30,Customers!$A$2:$F$301,3,FALSE),"") -> 56 | Q30: =IFERROR((G30-M30)/G30,0) -> 0.56137255 | R30: =IFERROR(VLOOKUP(C30,Customers!$A$2:$F$301,1,FALSE),"") -> CUST-0086 | S30: =IFERROR(VLOOKUP(D30,Products!$A$2:$F$61,6,FALSE),"") -> TRUE | T30: Q5.4 | U30: =_xludf.TEXTJOIN(" | ",TRUE,INDEX($X$2:$X$31,MATCH(1,$Z$2:$Z$31,0)),INDEX($X$2:$X$31,MATCH(2,$Z$2:$Z$31,0)),INDEX($X$2:$X$31,MATCH(3,$Z$2:$Z$31,0)),INDEX($X$2:$X$31,MATCH(4,$Z$2:$Z$31,0)),INDEX($X$2:$X$31,MATCH(5,$Z$2:$Z$31,0))) -> #NAME? | V30: TEXTJOIN top five reps | W30: =Sales_Reps!A30 -> R029 | X30: =Sales_Reps!B30 -> Arun Iyer | Y30: =SUMIF($E$2:$E$2001,W30,$I$2:$I$2001) -> 1016696.8 | Z30: =_xludf.RANK.EQ(Y30,$Y$2:$Y$31,0) -> #NAME? | BH30: =Products!A30 -> PROD-029 | BI30: =Products!B30 -> Ghee 1L | BJ30: =SUMIFS($I$2:$I$2001,$N$2:$N$2001,"West",$D$2:$D$2001,BH30) -> 118562.08 | BK30: =_xludf.RANK.EQ(BJ30,$BJ$2:$BJ$61,0) -> #NAME? | BL30: 0 | BM30: 0 | BN30: 0.018867925 | BO30: 0 | BP30: 0
A31: =Orders!A31 -> ORD-00030 | B31: =Orders!B31 -> 45367 | C31: =Orders!C31 -> CUST-0006 | D31: =Orders!D31 -> PROD-055 | E31: =Orders!E31 -> R005 | F31: =Orders!F31 -> 3 | G31: =Orders!G31 -> 2860 | H31: =Orders!H31 -> 25.8 | ... K31: =Orders!K31 -> Pune | L31: =IFERROR(VLOOKUP(D31,Products!$A$2:$F$61,3,FALSE),"") -> Sports | M31: =IFERROR(VLOOKUP(D31,Products!$A$2:$F$61,4,FALSE),"") -> 2028 | N31: =IFERROR(VLOOKUP(E31,Sales_Reps!$A$2:$E$31,3,FALSE),"") -> North | O31: =IFERROR(VLOOKUP(C31,Customers!$A$2:$F$301,5,FALSE),"") -> SMB | P31: =IFERROR(VLOOKUP(C31,Customers!$A$2:$F$301,3,FALSE),"") -> 44 | Q31: =IFERROR((G31-M31)/G31,0) -> 0.29090909 | R31: =IFERROR(VLOOKUP(C31,Customers!$A$2:$F$301,1,FALSE),"") -> CUST-0006 | S31: =IFERROR(VLOOKUP(D31,Products!$A$2:$F$61,6,FALSE),"") -> TRUE | T31: Q5.5 | U31: =_xludf.MAXIFS($I$2:$I$2001,$K$2:$K$2001,"Bengaluru",$L$2:$L$2001,"Grocery") -> #NAME? | V31: MAXIFS with two conditions | W31: =Sales_Reps!A31 -> R030 | X31: =Sales_Reps!B31 -> Kiran Bhatt | Y31: =SUMIF($E$2:$E$2001,W31,$I$2:$I$2001) -> 747624.37 | Z31: =_xludf.RANK.EQ(Y31,$Y$2:$Y$31,0) -> #NAME? | BH31: =Products!A31 -> PROD-030 | BI31: =Products!B31 -> Salt 1kg | BJ31: =SUMIFS($I$2:$I$2001,$N$2:$N$2001,"West",$D$2:$D$2001,BH31) -> 37405.14 | BK31: =_xludf.RANK.EQ(BJ31,$BJ$2:$BJ$61,0) -> #NAME? | BL31: 0 | BM31: 0 | BN31: 0.021276596 | BO31: 0 | BP31: 0
A32: =Orders!A32 -> ORD-00031 | B32: =Orders!B32 -> 45569 | C32: =Orders!C32 -> CUST-0241 | D32: =Orders!D32 -> PROD-030 | E32: =Orders!E32 -> R006 | F32: =Orders!F32 -> 7 | G32: =Orders!G32 -> 970 | H32: =Orders!H32 -> 29.8 | ... K32: =Orders!K32 -> Pune | L32: =IFERROR(VLOOKUP(D32,Products!$A$2:$F$61,3,FALSE),"") -> Grocery | M32: =IFERROR(VLOOKUP(D32,Products!$A$2:$F$61,4,FALSE),"") -> 434 | N32: =IFERROR(VLOOKUP(E32,Sales_Reps!$A$2:$E$31,3,FALSE),"") -> North | O32: =IFERROR(VLOOKUP(C32,Customers!$A$2:$F$301,5,FALSE),"") -> Corporate | P32: =IFERROR(VLOOKUP(C32,Customers!$A$2:$F$301,3,FALSE),"") -> 47 | Q32: =IFERROR((G32-M32)/G32,0) -> 0.55257732 | R32: =IFERROR(VLOOKUP(C32,Customers!$A$2:$F$301,1,FALSE),"") -> CUST-0241 | S32: =IFERROR(VLOOKUP(D32,Products!$A$2:$F$61,6,FALSE),"") -> TRUE | BH32: =Products!A32 -> PROD-031 | BI32: =Products!B32 -> Bed Sheet Set | BJ32: =SUMIFS($I$2:$I$2001,$N$2:$N$2001,"West",$D$2:$D$2001,BH32) -> 102321.36 | BK32: =_xludf.RANK.EQ(BJ32,$BJ$2:$BJ$61,0) -> #NAME? | BL32: 0 | BM32: 0 | BN32: 0.019607843 | BO32: 0 | BP32: 0
A33: =Orders!A33 -> ORD-00032 | B33: =Orders!B33 -> 45641 | C33: =Orders!C33 -> CUST-0035 | D33: =Orders!D33 -> PROD-021 | E33: =Orders!E33 -> R026 | F33: =Orders!F33 -> 4 | G33: =Orders!G33 -> 2760 | H33: =Orders!H33 -> 5.9 | ... K33: =Orders!K33 -> Hyderabad | L33: =IFERROR(VLOOKUP(D33,Products!$A$2:$F$61,3,FALSE),"") -> Grocery | M33: =IFERROR(VLOOKUP(D33,Products!$A$2:$F$61,4,FALSE),"") -> 1435 | N33: =IFERROR(VLOOKUP(E33,Sales_Reps!$A$2:$E$31,3,FALSE),"") -> West | O33: =IFERROR(VLOOKUP(C33,Customers!$A$2:$F$301,5,FALSE),"") -> Retail | P33: =IFERROR(VLOOKUP(C33,Customers!$A$2:$F$301,3,FALSE),"") -> 53 | Q33: =IFERROR((G33-M33)/G33,0) -> 0.48007246 | R33: =IFERROR(VLOOKUP(C33,Customers!$A$2:$F$301,1,FALSE),"") -> CUST-0035 | S33: =IFERROR(VLOOKUP(D33,Products!$A$2:$F$61,6,FALSE),"") -> TRUE | BH33: =Products!A33 -> PROD-032 | BI33: =Products!B33 -> Pillow Cover Pair | BJ33: =SUMIFS($I$2:$I$2001,$N$2:$N$2001,"West",$D$2:$D$2001,BH33) -> 20402.17 | BK33: =_xludf.RANK.EQ(BJ33,$BJ$2:$BJ$61,0) -> #NAME? | BL33: 0 | BM33: 0 | BN33: 0.019607843 | BO33: 0 | BP33: 0
A34: =Orders!A34 -> ORD-00033 | B34: =Orders!B34 -> 45343 | C34: =Orders!C34 -> CUST-0273 | D34: =Orders!D34 -> PROD-037 | E34: =Orders!E34 -> R009 | F34: =Orders!F34 -> 10 | G34: =Orders!G34 -> 660 | H34: =Orders!H34 -> 18.3 | ... K34: =Orders!K34 -> Hyderabad | L34: =IFERROR(VLOOKUP(D34,Products!$A$2:$F$61,3,FALSE),"") -> Home | M34: =IFERROR(VLOOKUP(D34,Products!$A$2:$F$61,4,FALSE),"") -> 329 | N34: =IFERROR(VLOOKUP(E34,Sales_Reps!$A$2:$E$31,3,FALSE),"") -> South | O34: =IFERROR(VLOOKUP(C34,Customers!$A$2:$F$301,5,FALSE),"") -> Corporate | P34: =IFERROR(VLOOKUP(C34,Customers!$A$2:$F$301,3,FALSE),"") -> 32 | Q34: =IFERROR((G34-M34)/G34,0) -> 0.50151515 | R34: =IFERROR(VLOOKUP(C34,Customers!$A$2:$F$301,1,FALSE),"") -> CUST-0273 | S34: =IFERROR(VLOOKUP(D34,Products!$A$2:$F$61,6,FALSE),"") -> TRUE | BH34: =Products!A34 -> PROD-033 | BI34: =Products!B34 -> Curtain Set | BJ34: =SUMIFS($I$2:$I$2001,$N$2:$N$2001,"West",$D$2:$D$2001,BH34) -> 137585.28 | BK34: =_xludf.RANK.EQ(BJ34,$BJ$2:$BJ$61,0) -> #NAME? | BL34: 0 | BM34: 0 | BN34: 0.023809524 | BO34: 0 | BP34: 0
A35: =Orders!A35 -> ORD-00034 | B35: =Orders!B35 -> 45576 | C35: =Orders!C35 -> CUST-0064 | D35: =Orders!D35 -> PROD-036 | E35: =Orders!E35 -> R019 | F35: =Orders!F35 -> 1 | G35: =Orders!G35 -> 3250 | H35: =Orders!H35 -> 10.7 | ... K35: =Orders!K35 -> Hyderabad | L35: =IFERROR(VLOOKUP(D35,Products!$A$2:$F$61,3,FALSE),"") -> Home | M35: =IFERROR(VLOOKUP(D35,Products!$A$2:$F$61,4,FALSE),"") -> 1556 | N35: =IFERROR(VLOOKUP(E35,Sales_Reps!$A$2:$E$31,3,FALSE),"") -> East | O35: =IFERROR(VLOOKUP(C35,Customers!$A$2:$F$301,5,FALSE),"") -> SMB | P35: =IFERROR(VLOOKUP(C35,Customers!$A$2:$F$301,3,FALSE),"") -> 40 | Q35: =IFERROR((G35-M35)/G35,0) -> 0.52123077 | R35: =IFERROR(VLOOKUP(C35,Customers!$A$2:$F$301,1,FALSE),"") -> CUST-0064 | S35: =IFERROR(VLOOKUP(D35,Products!$A$2:$F$61,6,FALSE),"") -> TRUE | BH35: =Products!A35 -> PROD-034 | BI35: =Products!B35 -> Kitchen Towel Set | BJ35: =SUMIFS($I$2:$I$2001,$N$2:$N$2001,"West",$D$2:$D$2001,BH35) -> 221112.08 | BK35: =_xludf.RANK.EQ(BJ35,$BJ$2:$BJ$61,0) -> #NAME? | BL35: 0 | BM35: 0 | BN35: 0.023809524 | BO35: 0 | BP35: 0
A36: =Orders!A36 -> ORD-00035 | B36: =Orders!B36 -> 45462 | C36: =Orders!C36 -> CUST-0118 | D36: =Orders!D36 -> PROD-048 | E36: =Orders!E36 -> R019 | F36: =Orders!F36 -> 8 | G36: =Orders!G36 -> 5100 | H36: =Orders!H36 -> 26.4 | ... K36: =Orders!K36 -> Hyderabad | L36: =IFERROR(VLOOKUP(D36,Products!$A$2:$F$61,3,FALSE),"") -> Beauty | M36: =IFERROR(VLOOKUP(D36,Products!$A$2:$F$61,4,FALSE),"") -> 2237 | N36: =IFERROR(VLOOKUP(E36,Sales_Reps!$A$2:$E$31,3,FALSE),"") -> East | O36: =IFERROR(VLOOKUP(C36,Customers!$A$2:$F$301,5,FALSE),"") -> Retail | P36: =IFERROR(VLOOKUP(C36,Customers!$A$2:$F$301,3,FALSE),"") -> 26 | Q36: =IFERROR((G36-M36)/G36,0) -> 0.56137255 | R36: =IFERROR(VLOOKUP(C36,Customers!$A$2:$F$301,1,FALSE),"") -> CUST-0118 | S36: =IFERROR(VLOOKUP(D36,Products!$A$2:$F$61,6,FALSE),"") -> TRUE | BH36: =Products!A36 -> PROD-035 | BI36: =Products!B36 -> Doormat | BJ36: =SUMIFS($I$2:$I$2001,$N$2:$N$2001,"West",$D$2:$D$2001,BH36) -> 26929.54 | BK36: =_xludf.RANK.EQ(BJ36,$BJ$2:$BJ$61,0) -> #NAME? | BL36: 0 | BM36: 0 | BN36: 0.019607843 | BO36: 0 | BP36: 0
A37: =Orders!A37 -> ORD-00036 | B37: =Orders!B37 -> 45442 | C37: =Orders!C37 -> CUST-0013 | D37: =Orders!D37 -> PROD-040 | E37: =Orders!E37 -> R021 | F37: =Orders!F37 -> 1 | G37: =Orders!G37 -> 1080 | H37: =Orders!H37 -> 5.1 | ... K37: =Orders!K37 -> Delhi | L37: =IFERROR(VLOOKUP(D37,Products!$A$2:$F$61,3,FALSE),"") -> Home | M37: =IFERROR(VLOOKUP(D37,Products!$A$2:$F$61,4,FALSE),"") -> 519 | N37: =IFERROR(VLOOKUP(E37,Sales_Reps!$A$2:$E$31,3,FALSE),"") -> East | O37: =IFERROR(VLOOKUP(C37,Customers!$A$2:$F$301,5,FALSE),"") -> Retail | P37: =IFERROR(VLOOKUP(C37,Customers!$A$2:$F$301,3,FALSE),"") -> 41 | Q37: =IFERROR((G37-M37)/G37,0) -> 0.51944444 | R37: =IFERROR(VLOOKUP(C37,Customers!$A$2:$F$301,1,FALSE),"") -> CUST-0013 | S37: =IFERROR(VLOOKUP(D37,Products!$A$2:$F$61,6,FALSE),"") -> TRUE | BH37: =Products!A37 -> PROD-036 | BI37: =Products!B37 -> Wall Clock | BJ37: =SUMIFS($I$2:$I$2001,$N$2:$N$2001,"West",$D$2:$D$2001,BH37) -> 88426 | BK37: =_xludf.RANK.EQ(BJ37,$BJ$2:$BJ$61,0) -> #NAME? | BL37: 0 | BM37: 0 | BN37: 0.018518519 | BO37: 0 | BP37: 0
A38: =Orders!A38 -> ORD-00037 | B38: =Orders!B38 -> 45646 | C38: =Orders!C38 -> CUST-0177 | D38: =Orders!D38 -> PROD-038 | E38: =Orders!E38 -> R009 | F38: =Orders!F38 -> 2 | G38: =Orders!G38 -> 5490 | H38: =Orders!H38 -> 21.1 | ... K38: =Orders!K38 -> Mumbai | L38: =IFERROR(VLOOKUP(D38,Products!$A$2:$F$61,3,FALSE),"") -> Home | M38: =IFERROR(VLOOKUP(D38,Products!$A$2:$F$61,4,FALSE),"") -> 2549 | N38: =IFERROR(VLOOKUP(E38,Sales_Reps!$A$2:$E$31,3,FALSE),"") -> South | O38: =IFERROR(VLOOKUP(C38,Customers!$A$2:$F$301,5,FALSE),"") -> SMB | P38: =IFERROR(VLOOKUP(C38,Customers!$A$2:$F$301,3,FALSE),"") -> 36 | Q38: =IFERROR((G38-M38)/G38,0) -> 0.53570128 | R38: =IFERROR(VLOOKUP(C38,Customers!$A$2:$F$301,1,FALSE),"") -> CUST-0177 | S38: =IFERROR(VLOOKUP(D38,Products!$A$2:$F$61,6,FALSE),"") -> TRUE | BH38: =Products!A38 -> PROD-037 | BI38: =Products!B38 -> Table Lamp | BJ38: =SUMIFS($I$2:$I$2001,$N$2:$N$2001,"West",$D$2:$D$2001,BH38) -> 13841.52 | BK38: =_xludf.RANK.EQ(BJ38,$BJ$2:$BJ$61,0) -> #NAME? | BL38: 0 | BM38: 0 | BN38: 0.021276596 | BO38: 0 | BP38: 0
A39: =Orders!A39 -> ORD-00038 | B39: =Orders!B39 -> 45478 | C39: =Orders!C39 -> CUST-0186 | D39: =Orders!D39 -> PROD-060 | E39: =Orders!E39 -> R001 | F39: =Orders!F39 -> 7 | G39: =Orders!G39 -> 190 | H39: =Orders!H39 -> 28.7 | ... K39: =Orders!K39 -> Bengaluru | L39: =IFERROR(VLOOKUP(D39,Products!$A$2:$F$61,3,FALSE),"") -> Sports | M39: =IFERROR(VLOOKUP(D39,Products!$A$2:$F$61,4,FALSE),"") -> 147 | N39: =IFERROR(VLOOKUP(E39,Sales_Reps!$A$2:$E$31,3,FALSE),"") -> North | O39: =IFERROR(VLOOKUP(C39,Customers!$A$2:$F$301,5,FALSE),"") -> Retail | P39: =IFERROR(VLOOKUP(C39,Customers!$A$2:$F$301,3,FALSE),"") -> 42 | Q39: =IFERROR((G39-M39)/G39,0) -> 0.22631579 | R39: =IFERROR(VLOOKUP(C39,Customers!$A$2:$F$301,1,FALSE),"") -> CUST-0186 | S39: =IFERROR(VLOOKUP(D39,Products!$A$2:$F$61,6,FALSE),"") -> TRUE | BH39: =Products!A39 -> PROD-038 | BI39: =Products!B39 -> Storage Box | BJ39: =SUMIFS($I$2:$I$2001,$N$2:$N$2001,"West",$D$2:$D$2001,BH39) -> 119445.93 | BK39: =_xludf.RANK.EQ(BJ39,$BJ$2:$BJ$61,0) -> #NAME? | BL39: 0 | BM39: 0 | BN39: 0.018518519 | BO39: 0 | BP39: 0
A40: =Orders!A40 -> ORD-00039 | B40: =Orders!B40 -> 45355 | C40: =Orders!C40 -> CUST-0069 | D40: =Orders!D40 -> PROD-058 | E40: =Orders!E40 -> R015 | F40: =Orders!F40 -> 6 | G40: =Orders!G40 -> 2400 | H40: =Orders!H40 -> 2.7 | ... K40: =Orders!K40 -> Chennai | L40: =IFERROR(VLOOKUP(D40,Products!$A$2:$F$61,3,FALSE),"") -> Sports | M40: =IFERROR(VLOOKUP(D40,Products!$A$2:$F$61,4,FALSE),"") -> 974 | N40: =IFERROR(VLOOKUP(E40,Sales_Reps!$A$2:$E$31,3,FALSE),"") -> South | O40: =IFERROR(VLOOKUP(C40,Customers!$A$2:$F$301,5,FALSE),"") -> Retail | P40: =IFERROR(VLOOKUP(C40,Customers!$A$2:$F$301,3,FALSE),"") -> 51 | Q40: =IFERROR((G40-M40)/G40,0) -> 0.59416667 | R40: =IFERROR(VLOOKUP(C40,Customers!$A$2:$F$301,1,FALSE),"") -> CUST-0069 | S40: =IFERROR(VLOOKUP(D40,Products!$A$2:$F$61,6,FALSE),"") -> TRUE | BH40: =Products!A40 -> PROD-039 | BI40: =Products!B40 -> Photo Frame | BJ40: =SUMIFS($I$2:$I$2001,$N$2:$N$2001,"West",$D$2:$D$2001,BH40) -> 177512.66 | BK40: =_xludf.RANK.EQ(BJ40,$BJ$2:$BJ$61,0) -> #NAME? | BL40: 0 | BM40: 0 | BN40: 0.021276596 | BO40: 0 | BP40: 0
A41: =Orders!A41 -> ORD-00040 | B41: =Orders!B41 -> 45599 | C41: =Orders!C41 -> CUST-0283 | D41: =Orders!D41 -> PROD-044 | E41: =Orders!E41 -> R023 | F41: =Orders!F41 -> 9 | G41: =Orders!G41 -> 1650 | H41: =Orders!H41 -> 11.6 | ... K41: =Orders!K41 -> Delhi | L41: =IFERROR(VLOOKUP(D41,Products!$A$2:$F$61,3,FALSE),"") -> Beauty | M41: =IFERROR(VLOOKUP(D41,Products!$A$2:$F$61,4,FALSE),"") -> 1222 | N41: =IFERROR(VLOOKUP(E41,Sales_Reps!$A$2:$E$31,3,FALSE),"") -> East | O41: =IFERROR(VLOOKUP(C41,Customers!$A$2:$F$301,5,FALSE),"") -> SMB | P41: =IFERROR(VLOOKUP(C41,Customers!$A$2:$F$301,3,FALSE),"") -> 50 | Q41: =IFERROR((G41-M41)/G41,0) -> 0.25939394 | R41: =IFERROR(VLOOKUP(C41,Customers!$A$2:$F$301,1,FALSE),"") -> CUST-0283 | S41: =IFERROR(VLOOKUP(D41,Products!$A$2:$F$61,6,FALSE),"") -> TRUE | BH41: =Products!A41 -> PROD-040 | BI41: =Products!B41 -> Cushion Cover | BJ41: =SUMIFS($I$2:$I$2001,$N$2:$N$2001,"West",$D$2:$D$2001,BH41) -> 47831.04 | BK41: =_xludf.RANK.EQ(BJ41,$BJ$2:$BJ$61,0) -> #NAME? | BL41: 0 | BM41: 0 | BN41: 0.018867925 | BO41: 0 | BP41: 0
A42: =Orders!A42 -> ORD-00041 | B42: =Orders!B42 -> 45606 | C42: =Orders!C42 -> CUST-9507 | D42: =Orders!D42 -> PROD-038 | E42: =Orders!E42 -> R006 | F42: =Orders!F42 -> 4 | G42: =Orders!G42 -> 5490 | H42: =Orders!H42 -> 12.8 | ... K42: =Orders!K42 -> Chennai | L42: =IFERROR(VLOOKUP(D42,Products!$A$2:$F$61,3,FALSE),"") -> Home | M42: =IFERROR(VLOOKUP(D42,Products!$A$2:$F$61,4,FALSE),"") -> 2549 | N42: =IFERROR(VLOOKUP(E42,Sales_Reps!$A$2:$E$31,3,FALSE),"") -> North | O42: =IFERROR(VLOOKUP(C42,Customers!$A$2:$F$301,5,FALSE),"") | P42: =IFERROR(VLOOKUP(C42,Customers!$A$2:$F$301,3,FALSE),"") | Q42: =IFERROR((G42-M42)/G42,0) -> 0.53570128 | R42: =IFERROR(VLOOKUP(C42,Customers!$A$2:$F$301,1,FALSE),"") | S42: =IFERROR(VLOOKUP(D42,Products!$A$2:$F$61,6,FALSE),"") -> TRUE | BH42: =Products!A42 -> PROD-041 | BI42: =Products!B42 -> Face Wash 100ml | BJ42: =SUMIFS($I$2:$I$2001,$N$2:$N$2001,"West",$D$2:$D$2001,BH42) -> 80488.1 | BK42: =_xludf.RANK.EQ(BJ42,$BJ$2:$BJ$61,0) -> #NAME? | BL42: 0 | BM42: 0 | BN42: 0.021276596 | BO42: 1 | BP42: 0
A43: =Orders!A43 -> ORD-00042 | B43: =Orders!B43 -> 45432 | C43: =Orders!C43 -> CUST-0053 | D43: =Orders!D43 -> PROD-046 | E43: =Orders!E43 -> R014 | F43: =Orders!F43 -> 10 | G43: =Orders!G43 -> 4880 | H43: =Orders!H43 -> 12.7 | ... K43: =Orders!K43 -> Delhi | L43: =IFERROR(VLOOKUP(D43,Products!$A$2:$F$61,3,FALSE),"") -> Beauty | M43: =IFERROR(VLOOKUP(D43,Products!$A$2:$F$61,4,FALSE),"") -> 2768 | N43: =IFERROR(VLOOKUP(E43,Sales_Reps!$A$2:$E$31,3,FALSE),"") -> South | O43: =IFERROR(VLOOKUP(C43,Customers!$A$2:$F$301,5,FALSE),"") -> Retail | P43: =IFERROR(VLOOKUP(C43,Customers!$A$2:$F$301,3,FALSE),"") -> 53 | Q43: =IFERROR((G43-M43)/G43,0) -> 0.43278689 | R43: =IFERROR(VLOOKUP(C43,Customers!$A$2:$F$301,1,FALSE),"") -> CUST-0053 | S43: =IFERROR(VLOOKUP(D43,Products!$A$2:$F$61,6,FALSE),"") -> TRUE | BH43: =Products!A43 -> PROD-042 | BI43: =Products!B43 -> Moisturizer 200ml | BJ43: =SUMIFS($I$2:$I$2001,$N$2:$N$2001,"West",$D$2:$D$2001,BH43) -> 138799.19 | BK43: =_xludf.RANK.EQ(BJ43,$BJ$2:$BJ$61,0) -> #NAME? | BL43: 0 | BM43: 0 | BN43: 0.018867925 | BO43: 0 | BP43: 0
... A61: =Orders!A61 -> ORD-00060 | B61: =Orders!B61 -> 45425 | C61: =Orders!C61 -> CUST-0263 | D61: =Orders!D61 -> PROD-039 | E61: =Orders!E61 -> R029 | F61: =Orders!F61 -> 4 | G61: =Orders!G61 -> 4610 | H61: =Orders!H61 -> 26.9 | ... K61: =Orders!K61 -> Mumbai | L61: =IFERROR(VLOOKUP(D61,Products!$A$2:$F$61,3,FALSE),"") -> Home | M61: =IFERROR(VLOOKUP(D61,Products!$A$2:$F$61,4,FALSE),"") -> 1850 | N61: =IFERROR(VLOOKUP(E61,Sales_Reps!$A$2:$E$31,3,FALSE),"") -> West | O61: =IFERROR(VLOOKUP(C61,Customers!$A$2:$F$301,5,FALSE),"") -> Retail | P61: =IFERROR(VLOOKUP(C61,Customers!$A$2:$F$301,3,FALSE),"") -> 40 | Q61: =IFERROR((G61-M61)/G61,0) -> 0.59869848 | R61: =IFERROR(VLOOKUP(C61,Customers!$A$2:$F$301,1,FALSE),"") -> CUST-0263 | S61: =IFERROR(VLOOKUP(D61,Products!$A$2:$F$61,6,FALSE),"") -> TRUE | BH61: =Products!A61 -> PROD-060 | BI61: =Products!B61 -> Gym Gloves | BJ61: =SUMIFS($I$2:$I$2001,$N$2:$N$2001,"West",$D$2:$D$2001,BH61) -> 7838.26 | BK61: =_xludf.RANK.EQ(BJ61,$BJ$2:$BJ$61,0) -> #NAME? | BL61: 0 | BM61: 0 | BN61: 0.018867925 | BO61: 0 | BP61: 0
A62: =Orders!A62 -> ORD-00061 | B62: =Orders!B62 -> 45589 | C62: =Orders!C62 -> CUST-0203 | D62: =Orders!D62 -> PROD-040 | E62: =Orders!E62 -> R011 | F62: =Orders!F62 -> 8 | G62: =Orders!G62 -> 1080 | H62: =Orders!H62 -> 28.4 | ... K62: =Orders!K62 -> Chennai | L62: =IFERROR(VLOOKUP(D62,Products!$A$2:$F$61,3,FALSE),"") -> Home | M62: =IFERROR(VLOOKUP(D62,Products!$A$2:$F$61,4,FALSE),"") -> 519 | N62: =IFERROR(VLOOKUP(E62,Sales_Reps!$A$2:$E$31,3,FALSE),"") -> South | O62: =IFERROR(VLOOKUP(C62,Customers!$A$2:$F$301,5,FALSE),"") -> SMB | P62: =IFERROR(VLOOKUP(C62,Customers!$A$2:$F$301,3,FALSE),"") -> 55 | Q62: =IFERROR((G62-M62)/G62,0) -> 0.51944444 | R62: =IFERROR(VLOOKUP(C62,Customers!$A$2:$F$301,1,FALSE),"") -> CUST-0203 | S62: =IFERROR(VLOOKUP(D62,Products!$A$2:$F$61,6,FALSE),"") -> TRUE | BL62: 0 | BM62: 0 | BN62: 0.019607843 | BO62: 0 | BP62: 0
A63: =Orders!A63 -> ORD-00062 | B63: =Orders!B63 -> 45488 | C63: =Orders!C63 -> CUST-0258 | D63: =Orders!D63 -> PROD-045 | E63: =Orders!E63 -> R006 | F63: =Orders!F63 -> 10 | G63: =Orders!G63 -> 3020 | H63: =Orders!H63 -> 25.4 | ... K63: =Orders!K63 -> Pune | L63: =IFERROR(VLOOKUP(D63,Products!$A$2:$F$61,3,FALSE),"") -> Beauty | M63: =IFERROR(VLOOKUP(D63,Products!$A$2:$F$61,4,FALSE),"") -> 1626 | N63: =IFERROR(VLOOKUP(E63,Sales_Reps!$A$2:$E$31,3,FALSE),"") -> North | O63: =IFERROR(VLOOKUP(C63,Customers!$A$2:$F$301,5,FALSE),"") -> Retail | P63: =IFERROR(VLOOKUP(C63,Customers!$A$2:$F$301,3,FALSE),"") -> 44 | Q63: =IFERROR((G63-M63)/G63,0) -> 0.4615894 | R63: =IFERROR(VLOOKUP(C63,Customers!$A$2:$F$301,1,FALSE),"") -> CUST-0258 | S63: =IFERROR(VLOOKUP(D63,Products!$A$2:$F$61,6,FALSE),"") -> TRUE | BL63: 0 | BM63: 0 | BN63: 0.018867925 | BO63: 0 | BP63: 0
A64: =Orders!A64 -> ORD-00063 | B64: =Orders!B64 -> 45465 | C64: =Orders!C64 -> CUST-0282 | D64: =Orders!D64 -> PROD-008 | E64: =Orders!E64 -> R017 | F64: =Orders!F64 -> 7 | G64: =Orders!G64 -> 2660 | H64: =Orders!H64 -> 5.3 | ... K64: =Orders!K64 -> Hyderabad | L64: =IFERROR(VLOOKUP(D64,Products!$A$2:$F$61,3,FALSE),"") -> Electronics | M64: =IFERROR(VLOOKUP(D64,Products!$A$2:$F$61,4,FALSE),"") -> 1259 | N64: =IFERROR(VLOOKUP(E64,Sales_Reps!$A$2:$E$31,3,FALSE),"") -> East | O64: =IFERROR(VLOOKUP(C64,Customers!$A$2:$F$301,5,FALSE),"") -> Corporate | P64: =IFERROR(VLOOKUP(C64,Customers!$A$2:$F$301,3,FALSE),"") -> 29 | Q64: =IFERROR((G64-M64)/G64,0) -> 0.52669173 | R64: =IFERROR(VLOOKUP(C64,Customers!$A$2:$F$301,1,FALSE),"") -> CUST-0282 | S64: =IFERROR(VLOOKUP(D64,Products!$A$2:$F$61,6,FALSE),"") -> FALSE | BL64: 0 | BM64: 0 | BN64: 0.018518519 | BO64: 0 | BP64: 1
A65: =Orders!A65 -> ORD-00064 | B65: =Orders!B65 -> 45599 | C65: =Orders!C65 -> CUST-0168 | D65: =Orders!D65 -> PROD-005 | E65: =Orders!E65 -> R003 | F65: =Orders!F65 -> 9 | G65: =Orders!G65 -> 300 | H65: =Orders!H65 -> 25.3 | ... K65: =Orders!K65 -> Pune | L65: =IFERROR(VLOOKUP(D65,Products!$A$2:$F$61,3,FALSE),"") -> Electronics | M65: =IFERROR(VLOOKUP(D65,Products!$A$2:$F$61,4,FALSE),"") -> 128 | N65: =IFERROR(VLOOKUP(E65,Sales_Reps!$A$2:$E$31,3,FALSE),"") -> North | O65: =IFERROR(VLOOKUP(C65,Customers!$A$2:$F$301,5,FALSE),"") -> Retail | P65: =IFERROR(VLOOKUP(C65,Customers!$A$2:$F$301,3,FALSE),"") -> 25 | Q65: =IFERROR((G65-M65)/G65,0) -> 0.57333333 | R65: =IFERROR(VLOOKUP(C65,Customers!$A$2:$F$301,1,FALSE),"") -> CUST-0168 | S65: =IFERROR(VLOOKUP(D65,Products!$A$2:$F$61,6,FALSE),"") -> TRUE | BL65: 0 | BM65: 0 | BN65: 0.019607843 | BO65: 0 | BP65: 0
A66: =Orders!A66 -> ORD-00065 | B66: =Orders!B66 -> 45317 | C66: =Orders!C66 -> CUST-0040 | D66: =Orders!D66 -> PROD-010 | E66: =Orders!E66 -> R022 | F66: =Orders!F66 -> 10 | G66: =Orders!G66 -> 2640 | H66: =Orders!H66 -> 18.7 | ... K66: =Orders!K66 -> Chennai | L66: =IFERROR(VLOOKUP(D66,Products!$A$2:$F$61,3,FALSE),"") -> Electronics | M66: =IFERROR(VLOOKUP(D66,Products!$A$2:$F$61,4,FALSE),"") -> 1149 | N66: =IFERROR(VLOOKUP(E66,Sales_Reps!$A$2:$E$31,3,FALSE),"") -> East | O66: =IFERROR(VLOOKUP(C66,Customers!$A$2:$F$301,5,FALSE),"") -> Retail | P66: =IFERROR(VLOOKUP(C66,Customers!$A$2:$F$301,3,FALSE),"") -> 28 | Q66: =IFERROR((G66-M66)/G66,0) -> 0.56477273 | R66: =IFERROR(VLOOKUP(C66,Customers!$A$2:$F$301,1,FALSE),"") -> CUST-0040 | S66: =IFERROR(VLOOKUP(D66,Products!$A$2:$F$61,6,FALSE),"") -> TRUE | BL66: 0 | BM66: 0 | BN66: 0.018867925 | BO66: 0 | BP66: 0
A67: =Orders!A67 -> ORD-00066 | B67: =Orders!B67 -> 45462 | C67: =Orders!C67 -> CUST-0283 | D67: =Orders!D67 -> PROD-020 | E67: =Orders!E67 -> R020 | F67: =Orders!F67 -> 8 | G67: =Orders!G67 -> 820 | H67: =Orders!H67 -> 24 | ... K67: =Orders!K67 -> Delhi | L67: =IFERROR(VLOOKUP(D67,Products!$A$2:$F$61,3,FALSE),"") -> Apparel | M67: =IFERROR(VLOOKUP(D67,Products!$A$2:$F$61,4,FALSE),"") -> 391 | N67: =IFERROR(VLOOKUP(E67,Sales_Reps!$A$2:$E$31,3,FALSE),"") -> East | O67: =IFERROR(VLOOKUP(C67,Customers!$A$2:$F$301,5,FALSE),"") -> SMB | P67: =IFERROR(VLOOKUP(C67,Customers!$A$2:$F$301,3,FALSE),"") -> 50 | Q67: =IFERROR((G67-M67)/G67,0) -> 0.52317073 | R67: =IFERROR(VLOOKUP(C67,Customers!$A$2:$F$301,1,FALSE),"") -> CUST-0283 | S67: =IFERROR(VLOOKUP(D67,Products!$A$2:$F$61,6,FALSE),"") -> TRUE | BL67: 0 | BM67: 0 | BN67: 0.023809524 | BO67: 0 | BP67: 0
A68: =Orders!A68 -> ORD-00067 | B68: =Orders!B68 -> 45499 | C68: =Orders!C68 -> CUST-0202 | D68: =Orders!D68 -> PROD-021 | E68: =Orders!E68 -> R028 | F68: =Orders!F68 -> 1 | G68: =Orders!G68 -> 2760 | H68: =Orders!H68 -> 4.8 | ... K68: =Orders!K68 -> Chennai | L68: =IFERROR(VLOOKUP(D68,Products!$A$2:$F$61,3,FALSE),"") -> Grocery | M68: =IFERROR(VLOOKUP(D68,Products!$A$2:$F$61,4,FALSE),"") -> 1435 | N68: =IFERROR(VLOOKUP(E68,Sales_Reps!$A$2:$E$31,3,FALSE),"") -> West | O68: =IFERROR(VLOOKUP(C68,Customers!$A$2:$F$301,5,FALSE),"") -> Retail | P68: =IFERROR(VLOOKUP(C68,Customers!$A$2:$F$301,3,FALSE),"") -> 39 | Q68: =IFERROR((G68-M68)/G68,0) -> 0.48007246 | R68: =IFERROR(VLOOKUP(C68,Customers!$A$2:$F$301,1,FALSE),"") -> CUST-0202 | S68: =IFERROR(VLOOKUP(D68,Products!$A$2:$F$61,6,FALSE),"") -> TRUE | BL68: 0 | BM68: 0 | BN68: 0.023809524 | BO68: 0 | BP68: 0
A69: =Orders!A69 -> ORD-00068 | B69: =Orders!B69 -> 45328 | C69: =Orders!C69 -> CUST-0161 | D69: =Orders!D69 -> PROD-014 | E69: =Orders!E69 -> R017 | F69: =Orders!F69 -> 2 | G69: =Orders!G69 -> 3620 | H69: =Orders!H69 -> 19.1 | ... K69: =Orders!K69 -> Chennai | L69: =IFERROR(VLOOKUP(D69,Products!$A$2:$F$61,3,FALSE),"") -> Apparel | M69: =IFERROR(VLOOKUP(D69,Products!$A$2:$F$61,4,FALSE),"") -> 2509 | N69: =IFERROR(VLOOKUP(E69,Sales_Reps!$A$2:$E$31,3,FALSE),"") -> East | O69: =IFERROR(VLOOKUP(C69,Customers!$A$2:$F$301,5,FALSE),"") -> Retail | P69: =IFERROR(VLOOKUP(C69,Customers!$A$2:$F$301,3,FALSE),"") -> 38 | Q69: =IFERROR((G69-M69)/G69,0) -> 0.30690608 | R69: =IFERROR(VLOOKUP(C69,Customers!$A$2:$F$301,1,FALSE),"") -> CUST-0161 | S69: =IFERROR(VLOOKUP(D69,Products!$A$2:$F$61,6,FALSE),"") -> TRUE | BL69: 0 | BM69: 0 | BN69: 0.023809524 | BO69: 0 | BP69: 0
A70: =Orders!A70 -> ORD-00069 | B70: =Orders!B70 -> 45459 | C70: =Orders!C70 -> CUST-0033 | D70: =Orders!D70 -> PROD-016 | E70: =Orders!E70 -> R025 | F70: =Orders!F70 -> 1 | G70: =Orders!G70 -> 620 | H70: =Orders!H70 -> 1 | ... K70: =Orders!K70 -> Delhi | L70: =IFERROR(VLOOKUP(D70,Products!$A$2:$F$61,3,FALSE),"") -> Apparel | M70: =IFERROR(VLOOKUP(D70,Products!$A$2:$F$61,4,FALSE),"") -> 396 | N70: =IFERROR(VLOOKUP(E70,Sales_Reps!$A$2:$E$31,3,FALSE),"") -> West | O70: =IFERROR(VLOOKUP(C70,Customers!$A$2:$F$301,5,FALSE),"") -> Retail | P70: =IFERROR(VLOOKUP(C70,Customers!$A$2:$F$301,3,FALSE),"") -> 35 | Q70: =IFERROR((G70-M70)/G70,0) -> 0.36129032 | R70: =IFERROR(VLOOKUP(C70,Customers!$A$2:$F$301,1,FALSE),"") -> CUST-0033 | S70: =IFERROR(VLOOKUP(D70,Products!$A$2:$F$61,6,FALSE),"") -> TRUE | BL70: 0 | BM70: 0 | BN70: 0.018867925 | BO70: 0 | BP70: 0
A71: =Orders!A71 -> ORD-00070 | B71: =Orders!B71 -> 45398 | C71: =Orders!C71 -> CUST-0191 | D71: =Orders!D71 -> PROD-033 | E71: =Orders!E71 -> R030 | F71: =Orders!F71 -> 1 | G71: =Orders!G71 -> 2030 | H71: =Orders!H71 -> 3.3 | ... K71: =Orders!K71 -> Hyderabad | L71: =IFERROR(VLOOKUP(D71,Products!$A$2:$F$61,3,FALSE),"") -> Home | M71: =IFERROR(VLOOKUP(D71,Products!$A$2:$F$61,4,FALSE),"") -> 1143 | N71: =IFERROR(VLOOKUP(E71,Sales_Reps!$A$2:$E$31,3,FALSE),"") -> West | O71: =IFERROR(VLOOKUP(C71,Customers!$A$2:$F$301,5,FALSE),"") -> SMB | P71: =IFERROR(VLOOKUP(C71,Customers!$A$2:$F$301,3,FALSE),"") -> 43 | Q71: =IFERROR((G71-M71)/G71,0) -> 0.43694581 | R71: =IFERROR(VLOOKUP(C71,Customers!$A$2:$F$301,1,FALSE),"") -> CUST-0191 | S71: =IFERROR(VLOOKUP(D71,Products!$A$2:$F$61,6,FALSE),"") -> TRUE | BL71: 0 | BM71: 0 | BN71: 0.018518519 | BO71: 0 | BP71: 0
A72: =Orders!A72 -> ORD-00071 | B72: =Orders!B72 -> 45470 | C72: =Orders!C72 -> CUST-0180 | D72: =Orders!D72 -> PROD-012 | E72: =Orders!E72 -> R002 | F72: =Orders!F72 -> 10 | G72: =Orders!G72 -> 3160 | H72: =Orders!H72 -> 15.8 | ... K72: =Orders!K72 -> Chennai | L72: =IFERROR(VLOOKUP(D72,Products!$A$2:$F$61,3,FALSE),"") -> Apparel | M72: =IFERROR(VLOOKUP(D72,Products!$A$2:$F$61,4,FALSE),"") -> 1886 | N72: =IFERROR(VLOOKUP(E72,Sales_Reps!$A$2:$E$31,3,FALSE),"") -> North | O72: =IFERROR(VLOOKUP(C72,Customers!$A$2:$F$301,5,FALSE),"") -> Retail | P72: =IFERROR(VLOOKUP(C72,Customers!$A$2:$F$301,3,FALSE),"") -> 36 | Q72: =IFERROR((G72-M72)/G72,0) -> 0.40316456 | R72: =IFERROR(VLOOKUP(C72,Customers!$A$2:$F$301,1,FALSE),"") -> CUST-0180 | S72: =IFERROR(VLOOKUP(D72,Products!$A$2:$F$61,6,FALSE),"") -> TRUE | BL72: 0 | BM72: 0 | BN72: 0.023809524 | BO72: 0 | BP72: 0
A73: =Orders!A73 -> ORD-00072 | B73: =Orders!B73 -> 45346 | C73: =Orders!C73 -> CUST-0129 | D73: =Orders!D73 -> PROD-030 | E73: =Orders!E73 -> R001 | F73: =Orders!F73 -> 5 | G73: =Orders!G73 -> 970 | H73: =Orders!H73 -> 12.2 | ... K73: =Orders!K73 -> Hyderabad | L73: =IFERROR(VLOOKUP(D73,Products!$A$2:$F$61,3,FALSE),"") -> Grocery | M73: =IFERROR(VLOOKUP(D73,Products!$A$2:$F$61,4,FALSE),"") -> 434 | N73: =IFERROR(VLOOKUP(E73,Sales_Reps!$A$2:$E$31,3,FALSE),"") -> North | O73: =IFERROR(VLOOKUP(C73,Customers!$A$2:$F$301,5,FALSE),"") -> Retail | P73: =IFERROR(VLOOKUP(C73,Customers!$A$2:$F$301,3,FALSE),"") -> 29 | Q73: =IFERROR((G73-M73)/G73,0) -> 0.55257732 | R73: =IFERROR(VLOOKUP(C73,Customers!$A$2:$F$301,1,FALSE),"") -> CUST-0129 | S73: =IFERROR(VLOOKUP(D73,Products!$A$2:$F$61,6,FALSE),"") -> TRUE | BL73: 0 | BM73: 1 | BN73: 0.018518519 | BO73: 0 | BP73: 0
... A301: =Orders!A301 -> ORD-00300 | B301: =Orders!B301 -> 45635 | C301: =Orders!C301 -> CUST-0010 | D301: =Orders!D301 -> PROD-040 | E301: =Orders!E301 -> R004 | F301: =Orders!F301 -> 1 | G301: =Orders!G301 -> 1080 | H301: =Orders!H301 -> 13.9 | ... K301: =Orders!K301 -> Mumbai | L301: =IFERROR(VLOOKUP(D301,Products!$A$2:$F$61,3,FALSE),"") -> Home | M301: =IFERROR(VLOOKUP(D301,Products!$A$2:$F$61,4,FALSE),"") -> 519 | N301: =IFERROR(VLOOKUP(E301,Sales_Reps!$A$2:$E$31,3,FALSE),"") -> North | O301: =IFERROR(VLOOKUP(C301,Customers!$A$2:$F$301,5,FALSE),"") -> SMB | P301: =IFERROR(VLOOKUP(C301,Customers!$A$2:$F$301,3,FALSE),"") -> 61 | Q301: =IFERROR((G301-M301)/G301,0) -> 0.51944444 | R301: =IFERROR(VLOOKUP(C301,Customers!$A$2:$F$301,1,FALSE),"") -> CUST-0010 | S301: =IFERROR(VLOOKUP(D301,Products!$A$2:$F$61,6,FALSE),"") -> TRUE | BL301: 0 | BM301: 0 | BN301: 0.018518519 | BO301: 0 | BP301: 0
A302: =Orders!A302 -> ORD-00301 | B302: =Orders!B302 -> 45395 | C302: =Orders!C302 -> CUST-0036 | D302: =Orders!D302 -> PROD-033 | E302: =Orders!E302 -> R016 | F302: =Orders!F302 -> 7 | G302: =Orders!G302 -> 2030 | H302: =Orders!H302 -> 29.2 | ... K302: =Orders!K302 -> Mumbai | L302: =IFERROR(VLOOKUP(D302,Products!$A$2:$F$61,3,FALSE),"") -> Home | M302: =IFERROR(VLOOKUP(D302,Products!$A$2:$F$61,4,FALSE),"") -> 1143 | N302: =IFERROR(VLOOKUP(E302,Sales_Reps!$A$2:$E$31,3,FALSE),"") -> South | O302: =IFERROR(VLOOKUP(C302,Customers!$A$2:$F$301,5,FALSE),"") -> Retail | P302: =IFERROR(VLOOKUP(C302,Customers!$A$2:$F$301,3,FALSE),"") -> 35 | Q302: =IFERROR((G302-M302)/G302,0) -> 0.43694581 | R302: =IFERROR(VLOOKUP(C302,Customers!$A$2:$F$301,1,FALSE),"") -> CUST-0036 | S302: =IFERROR(VLOOKUP(D302,Products!$A$2:$F$61,6,FALSE),"") -> TRUE | BL302: 0 | BO302: 0 | BP302: 0
A303: =Orders!A303 -> ORD-00302 | B303: =Orders!B303 -> 45415 | C303: =Orders!C303 -> CUST-0259 | D303: =Orders!D303 -> PROD-059 | E303: =Orders!E303 -> R020 | F303: =Orders!F303 -> 6 | G303: =Orders!G303 -> 3780 | H303: =Orders!H303 -> 20.9 | ... K303: =Orders!K303 -> Mumbai | L303: =IFERROR(VLOOKUP(D303,Products!$A$2:$F$61,3,FALSE),"") -> Sports | M303: =IFERROR(VLOOKUP(D303,Products!$A$2:$F$61,4,FALSE),"") -> 1860 | N303: =IFERROR(VLOOKUP(E303,Sales_Reps!$A$2:$E$31,3,FALSE),"") -> East | O303: =IFERROR(VLOOKUP(C303,Customers!$A$2:$F$301,5,FALSE),"") -> Retail | P303: =IFERROR(VLOOKUP(C303,Customers!$A$2:$F$301,3,FALSE),"") -> 34 | Q303: =IFERROR((G303-M303)/G303,0) -> 0.50793651 | R303: =IFERROR(VLOOKUP(C303,Customers!$A$2:$F$301,1,FALSE),"") -> CUST-0259 | S303: =IFERROR(VLOOKUP(D303,Products!$A$2:$F$61,6,FALSE),"") -> TRUE | BL303: 0 | BO303: 0 | BP303: 0
A304: =Orders!A304 -> ORD-00303 | B304: =Orders!B304 -> 45653 | C304: =Orders!C304 -> CUST-0247 | D304: =Orders!D304 -> PROD-012 | E304: =Orders!E304 -> R016 | F304: =Orders!F304 -> 1 | G304: =Orders!G304 -> 3160 | H304: =Orders!H304 -> 10.7 | ... K304: =Orders!K304 -> Pune | L304: =IFERROR(VLOOKUP(D304,Products!$A$2:$F$61,3,FALSE),"") -> Apparel | M304: =IFERROR(VLOOKUP(D304,Products!$A$2:$F$61,4,FALSE),"") -> 1886 | N304: =IFERROR(VLOOKUP(E304,Sales_Reps!$A$2:$E$31,3,FALSE),"") -> South | O304: =IFERROR(VLOOKUP(C304,Customers!$A$2:$F$301,5,FALSE),"") -> SMB | P304: =IFERROR(VLOOKUP(C304,Customers!$A$2:$F$301,3,FALSE),"") -> 35 | Q304: =IFERROR((G304-M304)/G304,0) -> 0.40316456 | R304: =IFERROR(VLOOKUP(C304,Customers!$A$2:$F$301,1,FALSE),"") -> CUST-0247 | S304: =IFERROR(VLOOKUP(D304,Products!$A$2:$F$61,6,FALSE),"") -> TRUE | BL304: 0 | BO304: 0 | BP304: 0
A305: =Orders!A305 -> ORD-00881 | B305: =Orders!B305 -> 45564 | C305: =Orders!C305 -> CUST-0191 | D305: =Orders!D305 -> PROD-046 | E305: =Orders!E305 -> R010 | F305: =Orders!F305 -> 5 | G305: =Orders!G305 -> 4880 | H305: =Orders!H305 -> 11.4 | ... K305: =Orders!K305 -> Hyderabad | L305: =IFERROR(VLOOKUP(D305,Products!$A$2:$F$61,3,FALSE),"") -> Beauty | M305: =IFERROR(VLOOKUP(D305,Products!$A$2:$F$61,4,FALSE),"") -> 2768 | N305: =IFERROR(VLOOKUP(E305,Sales_Reps!$A$2:$E$31,3,FALSE),"") -> South | O305: =IFERROR(VLOOKUP(C305,Customers!$A$2:$F$301,5,FALSE),"") -> SMB | P305: =IFERROR(VLOOKUP(C305,Customers!$A$2:$F$301,3,FALSE),"") -> 43 | Q305: =IFERROR((G305-M305)/G305,0) -> 0.43278689 | R305: =IFERROR(VLOOKUP(C305,Customers!$A$2:$F$301,1,FALSE),"") -> CUST-0191 | S305: =IFERROR(VLOOKUP(D305,Products!$A$2:$F$61,6,FALSE),"") -> TRUE | BL305: 0.5 | BO305: 0 | BP305: 0
A306: =Orders!A306 -> ORD-00305 | B306: =Orders!B306 -> 45633 | C306: =Orders!C306 -> CUST-0167 | D306: =Orders!D306 -> PROD-031 | E306: =Orders!E306 -> R009 | F306: =Orders!F306 -> 9 | G306: =Orders!G306 -> 3730 | H306: =Orders!H306 -> 10 | ... K306: =Orders!K306 -> Delhi | L306: =IFERROR(VLOOKUP(D306,Products!$A$2:$F$61,3,FALSE),"") -> Home | M306: =IFERROR(VLOOKUP(D306,Products!$A$2:$F$61,4,FALSE),"") -> 2135 | N306: =IFERROR(VLOOKUP(E306,Sales_Reps!$A$2:$E$31,3,FALSE),"") -> South | O306: =IFERROR(VLOOKUP(C306,Customers!$A$2:$F$301,5,FALSE),"") -> Retail | P306: =IFERROR(VLOOKUP(C306,Customers!$A$2:$F$301,3,FALSE),"") -> 43 | Q306: =IFERROR((G306-M306)/G306,0) -> 0.42761394 | R306: =IFERROR(VLOOKUP(C306,Customers!$A$2:$F$301,1,FALSE),"") -> CUST-0167 | S306: =IFERROR(VLOOKUP(D306,Products!$A$2:$F$61,6,FALSE),"") -> TRUE | BL306: 0 | BO306: 0 | BP306: 0
A307: =Orders!A307 -> ORD-00306 | B307: =Orders!B307 -> 45309 | C307: =Orders!C307 -> CUST-0196 | D307: =Orders!D307 -> PROD-034 | E307: =Orders!E307 -> R004 | F307: =Orders!F307 -> 5 | G307: =Orders!G307 -> 5080 | H307: =Orders!H307 -> 15.3 | ... K307: =Orders!K307 -> Chennai | L307: =IFERROR(VLOOKUP(D307,Products!$A$2:$F$61,3,FALSE),"") -> Home | M307: =IFERROR(VLOOKUP(D307,Products!$A$2:$F$61,4,FALSE),"") -> 2459 | N307: =IFERROR(VLOOKUP(E307,Sales_Reps!$A$2:$E$31,3,FALSE),"") -> North | O307: =IFERROR(VLOOKUP(C307,Customers!$A$2:$F$301,5,FALSE),"") -> Retail | P307: =IFERROR(VLOOKUP(C307,Customers!$A$2:$F$301,3,FALSE),"") -> 26 | Q307: =IFERROR((G307-M307)/G307,0) -> 0.51594488 | R307: =IFERROR(VLOOKUP(C307,Customers!$A$2:$F$301,1,FALSE),"") -> CUST-0196 | S307: =IFERROR(VLOOKUP(D307,Products!$A$2:$F$61,6,FALSE),"") -> TRUE | BL307: 0 | BO307: 0 | BP307: 0
A308: =Orders!A308 -> ORD-00307 | B308: =Orders!B308 -> 45403 | C308: =Orders!C308 -> CUST-0182 | D308: =Orders!D308 -> PROD-042 | E308: =Orders!E308 -> R013 | F308: =Orders!F308 -> 9 | G308: =Orders!G308 -> 2290 | H308: =Orders!H308 -> 3.3 | ... K308: =Orders!K308 -> Mumbai | L308: =IFERROR(VLOOKUP(D308,Products!$A$2:$F$61,3,FALSE),"") -> Beauty | M308: =IFERROR(VLOOKUP(D308,Products!$A$2:$F$61,4,FALSE),"") -> 1219 | N308: =IFERROR(VLOOKUP(E308,Sales_Reps!$A$2:$E$31,3,FALSE),"") -> South | O308: =IFERROR(VLOOKUP(C308,Customers!$A$2:$F$301,5,FALSE),"") -> Retail | P308: =IFERROR(VLOOKUP(C308,Customers!$A$2:$F$301,3,FALSE),"") -> 54 | Q308: =IFERROR((G308-M308)/G308,0) -> 0.46768559 | R308: =IFERROR(VLOOKUP(C308,Customers!$A$2:$F$301,1,FALSE),"") -> CUST-0182 | S308: =IFERROR(VLOOKUP(D308,Products!$A$2:$F$61,6,FALSE),"") -> TRUE | BL308: 0 | BO308: 0 | BP308: 0
A309: =Orders!A309 -> ORD-00308 | B309: =Orders!B309 -> 45554 | C309: =Orders!C309 -> CUST-0246 | D309: =Orders!D309 -> PROD-008 | E309: =Orders!E309 -> R010 | F309: =Orders!F309 -> 5 | G309: =Orders!G309 -> 2660 | H309: =Orders!H309 -> 8.3 | ... K309: =Orders!K309 -> Delhi | L309: =IFERROR(VLOOKUP(D309,Products!$A$2:$F$61,3,FALSE),"") -> Electronics | M309: =IFERROR(VLOOKUP(D309,Products!$A$2:$F$61,4,FALSE),"") -> 1259 | N309: =IFERROR(VLOOKUP(E309,Sales_Reps!$A$2:$E$31,3,FALSE),"") -> South | O309: =IFERROR(VLOOKUP(C309,Customers!$A$2:$F$301,5,FALSE),"") -> SMB | P309: =IFERROR(VLOOKUP(C309,Customers!$A$2:$F$301,3,FALSE),"") -> 29 | Q309: =IFERROR((G309-M309)/G309,0) -> 0.52669173 | R309: =IFERROR(VLOOKUP(C309,Customers!$A$2:$F$301,1,FALSE),"") -> CUST-0246 | S309: =IFERROR(VLOOKUP(D309,Products!$A$2:$F$61,6,FALSE),"") -> FALSE | BL309: 0 | BO309: 0 | BP309: 1
A310: =Orders!A310 -> ORD-00309 | B310: =Orders!B310 -> 45529 | C310: =Orders!C310 -> CUST-0132 | D310: =Orders!D310 -> PROD-027 | E310: =Orders!E310 -> R025 | F310: =Orders!F310 -> 6 | G310: =Orders!G310 -> 3780 | H310: =Orders!H310 -> 28.3 | ... K310: =Orders!K310 -> Delhi | L310: =IFERROR(VLOOKUP(D310,Products!$A$2:$F$61,3,FALSE),"") -> Grocery | M310: =IFERROR(VLOOKUP(D310,Products!$A$2:$F$61,4,FALSE),"") -> 2436 | N310: =IFERROR(VLOOKUP(E310,Sales_Reps!$A$2:$E$31,3,FALSE),"") -> West | O310: =IFERROR(VLOOKUP(C310,Customers!$A$2:$F$301,5,FALSE),"") -> Retail | P310: =IFERROR(VLOOKUP(C310,Customers!$A$2:$F$301,3,FALSE),"") -> 41 | Q310: =IFERROR((G310-M310)/G310,0) -> 0.35555556 | R310: =IFERROR(VLOOKUP(C310,Customers!$A$2:$F$301,1,FALSE),"") -> CUST-0132 | S310: =IFERROR(VLOOKUP(D310,Products!$A$2:$F$61,6,FALSE),"") -> TRUE | BL310: 0 | BO310: 0 | BP310: 0
A311: =Orders!A311 -> ORD-00310 | B311: =Orders!B311 -> 45300 | C311: =Orders!C311 -> CUST-0153 | D311: =Orders!D311 -> PROD-021 | E311: =Orders!E311 -> R028 | F311: =Orders!F311 -> 5 | G311: =Orders!G311 -> 2760 | H311: =Orders!H311 -> 4.9 | ... K311: =Orders!K311 -> Mumbai | L311: =IFERROR(VLOOKUP(D311,Products!$A$2:$F$61,3,FALSE),"") -> Grocery | M311: =IFERROR(VLOOKUP(D311,Products!$A$2:$F$61,4,FALSE),"") -> 1435 | N311: =IFERROR(VLOOKUP(E311,Sales_Reps!$A$2:$E$31,3,FALSE),"") -> West | O311: =IFERROR(VLOOKUP(C311,Customers!$A$2:$F$301,5,FALSE),"") -> Retail | P311: =IFERROR(VLOOKUP(C311,Customers!$A$2:$F$301,3,FALSE),"") -> 35 | Q311: =IFERROR((G311-M311)/G311,0) -> 0.48007246 | R311: =IFERROR(VLOOKUP(C311,Customers!$A$2:$F$301,1,FALSE),"") -> CUST-0153 | S311: =IFERROR(VLOOKUP(D311,Products!$A$2:$F$61,6,FALSE),"") -> TRUE | BL311: 0 | BO311: 0 | BP311: 0
A312: =Orders!A312 -> ORD-00311 | B312: =Orders!B312 -> 45368 | C312: =Orders!C312 -> CUST-0139 | D312: =Orders!D312 -> PROD-041 | E312: =Orders!E312 -> R006 | F312: =Orders!F312 -> 8 | G312: =Orders!G312 -> 1540 | H312: =Orders!H312 -> 29.4 | ... K312: =Orders!K312 -> Hyderabad | L312: =IFERROR(VLOOKUP(D312,Products!$A$2:$F$61,3,FALSE),"") -> Beauty | M312: =IFERROR(VLOOKUP(D312,Products!$A$2:$F$61,4,FALSE),"") -> 647 | N312: =IFERROR(VLOOKUP(E312,Sales_Reps!$A$2:$E$31,3,FALSE),"") -> North | O312: =IFERROR(VLOOKUP(C312,Customers!$A$2:$F$301,5,FALSE),"") -> SMB | P312: =IFERROR(VLOOKUP(C312,Customers!$A$2:$F$301,3,FALSE),"") -> 65 | Q312: =IFERROR((G312-M312)/G312,0) -> 0.57987013 | R312: =IFERROR(VLOOKUP(C312,Customers!$A$2:$F$301,1,FALSE),"") -> CUST-0139 | S312: =IFERROR(VLOOKUP(D312,Products!$A$2:$F$61,6,FALSE),"") -> FALSE | BL312: 0 | BO312: 0 | BP312: 1
A313: =Orders!A313 -> ORD-00312 | B313: =Orders!B313 -> 45374 | C313: =Orders!C313 -> CUST-0256 | D313: =Orders!D313 -> PROD-046 | E313: =Orders!E313 -> R022 | F313: =Orders!F313 -> 1 | G313: =Orders!G313 -> 4880 | H313: =Orders!H313 -> 18.1 | ... K313: =Orders!K313 -> Hyderabad | L313: =IFERROR(VLOOKUP(D313,Products!$A$2:$F$61,3,FALSE),"") -> Beauty | M313: =IFERROR(VLOOKUP(D313,Products!$A$2:$F$61,4,FALSE),"") -> 2768 | N313: =IFERROR(VLOOKUP(E313,Sales_Reps!$A$2:$E$31,3,FALSE),"") -> East | O313: =IFERROR(VLOOKUP(C313,Customers!$A$2:$F$301,5,FALSE),"") -> Retail | P313: =IFERROR(VLOOKUP(C313,Customers!$A$2:$F$301,3,FALSE),"") -> 28 | Q313: =IFERROR((G313-M313)/G313,0) -> 0.43278689 | R313: =IFERROR(VLOOKUP(C313,Customers!$A$2:$F$301,1,FALSE),"") -> CUST-0256 | S313: =IFERROR(VLOOKUP(D313,Products!$A$2:$F$61,6,FALSE),"") -> TRUE | BL313: 0 | BO313: 0 | BP313: 0
... A2001: =Orders!A2001 -> ORD-02000 | B2001: =Orders!B2001 -> 45325 | C2001: =Orders!C2001 -> CUST-0238 | D2001: =Orders!D2001 -> PROD-034 | E2001: =Orders!E2001 -> R023 | F2001: =Orders!F2001 -> 6 | G2001: =Orders!G2001 -> 5080 | H2001: =Orders!H2001 -> 28.1 | ... K2001: =Orders!K2001 -> Delhi | L2001: =IFERROR(VLOOKUP(D2001,Products!$A$2:$F$61,3,FALSE),"") -> Home | M2001: =IFERROR(VLOOKUP(D2001,Products!$A$2:$F$61,4,FALSE),"") -> 2459 | N2001: =IFERROR(VLOOKUP(E2001,Sales_Reps!$A$2:$E$31,3,FALSE),"") -> East | O2001: =IFERROR(VLOOKUP(C2001,Customers!$A$2:$F$301,5,FALSE),"") -> Retail | P2001: =IFERROR(VLOOKUP(C2001,Customers!$A$2:$F$301,3,FALSE),"") -> 49 | Q2001: =IFERROR((G2001-M2001)/G2001,0) -> 0.51594488 | R2001: =IFERROR(VLOOKUP(C2001,Customers!$A$2:$F$301,1,FALSE),"") -> CUST-0238 | S2001: =IFERROR(VLOOKUP(D2001,Products!$A$2:$F$61,6,FALSE),"") -> TRUE | BL2001: 0 | BO2001: 0 | BP2001: 0
